{
    "mo-probs-11th-january-2018": {
        "00": {
            "artist": "Lena d'Água",
            "ratio": 9,
            "title": "Tao",
            "trackid": "J_HjiON-DeU"
        },
        "01": {
            "artist": "Sugai Ken",
            "ratio": 9,
            "title": "Wochikaeri to Uzume",
            "trackid": "0xVhBhdxVjU"
        },
        "02": {
            "artist": "Taeko Ohnuki",
            "ratio": -1,
            "title": "4-00 AM - 1978",
            "trackid": "YixAD9GIAuY",
            "uri": ""
        },
        "03": {
            "artist": "Satoshi & Makoto",
            "ratio": 9,
            "title": "Crepuscule Leger",
            "trackid": "nuHsXcmd6gg"
        },
        "04": {
            "artist": "Itsuroh Shimoda",
            "ratio": 9,
            "title": "Everybody Anyone (1974)",
            "trackid": "UqwYI9un1qc"
        },
        "05": {
            "artist": "Joseph Shabason",
            "ratio": 9,
            "title": "Looking Forward To Something, Dude",
            "trackid": "mFUw1htSh60"
        },
        "06": {
            "artist": "Laurence Vanay",
            "ratio": 9,
            "title": "Gate Way Evening Colours (1975) ► Lover's prayer",
            "trackid": "ar5sXdM9Jr8"
        },
        "07": {
            "artist": "Bennie Maupin",
            "ratio": 4,
            "title": "Penumbra",
            "trackid": "N9QYxXo8-cU"
        },
        "08": {
            "artist": "Alice Coltrane",
            "ratio": 9,
            "title": "Oceanic Beloved",
            "trackid": "iEYueIlUsdg"
        },
        "09": {
            "artist": "Marvin Gaye",
            "ratio": 9,
            "title": "After The Dance (Instrumental)",
            "trackid": "No6TOsf35T4"
        },
        "10": {
            "artist": "It Doesn't Make Sense",
            "ratio": 9,
            "title": "The Family Circle",
            "trackid": "-ThmJLUa5v0"
        },
        "11": {
            "artist": "Marsha Wilson",
            "ratio": 9,
            "title": "Love Is Gonna Get You",
            "trackid": "G10r9YMEnJM"
        },
        "12": {
            "artist": "Doreen Schaffer",
            "ratio": 5,
            "title": "This Love - Doreen & Brentford Disco Set - This Love (Ver.)",
            "trackid": "er2n_4FsEpI"
        },
        "13": {
            "artist": "Shawn Pittman",
            "ratio": 9,
            "title": "Dreams",
            "trackid": "XrQtwEyzyKk"
        }
    },
    "mo-probs-15th-may-2017": {
        "00": {
            "artist": "Whilst",
            "ratio": 9,
            "title": "Untitled From North Africa",
            "trackid": "WSRPLd48ekU"
        },
        "01": {
            "artist": "Telekom Electronic Beats",
            "ratio": 3,
            "title": "Mark Ernestus' Ndagga Rhythm Force \"Walo Walo\" Live",
            "trackid": "G4iKmXTfUv8"
        },
        "02": {
            "artist": "Zota Yinne",
            "ratio": 8,
            "title": "Algote Oho Jonas",
            "trackid": "BV2kU6u__f4"
        },
        "03": {
            "artist": "African Stone",
            "ratio": 9,
            "title": "Right Choice",
            "trackid": "ElGlR6MKh-Y"
        },
        "04": {
            "artist": "(1975) Natty Locks",
            "ratio": 9,
            "title": "Unite Dub",
            "trackid": "lhS4s249EVw"
        },
        "05": {
            "artist": "General Strike",
            "ratio": 9,
            "title": "Snowdrops",
            "trackid": "ZiwyyULXOuE"
        },
        "06": {
            "artist": "Michael Karoli & Polly Eltes",
            "ratio": 9,
            "title": "Deluge (The River)",
            "trackid": "RVk2ZQ68WJo"
        },
        "07": {
            "artist": "King Tubby & Harry Mudie",
            "ratio": 0,
            "title": "Jungle walk dub",
            "trackid": "uV3yxJzYtwk"
        },
        "08": {
            "artist": "Moebius & Plank",
            "ratio": 9,
            "title": "News",
            "trackid": "ZRxt6oUvXSg"
        },
        "09": {
            "artist": "Bernard Parmegiani",
            "ratio": 9,
            "title": "Incidences / Résonances",
            "trackid": "aaHcT-3ssI4"
        },
        "10": {
            "artist": "Dinosaur L",
            "ratio": 0,
            "title": "Go Bang! (Thank You Arthur Edit)",
            "trackid": "PxyXorZu9zo"
        },
        "11": {
            "artist": "23 Skidoo",
            "ratio": 9,
            "title": "Tearing Up the Plans Pt 1 - 1982 (Cut)",
            "trackid": "GrO6IfKMcag"
        },
        "12": {
            "artist": "Marion Brown",
            "ratio": 9,
            "title": "Sweet Earth Flying, Pt.1",
            "trackid": "niKhxl2zMoo"
        },
        "13": {
            "artist": "Lou Harrison",
            "ratio": 9,
            "title": "Four Pieces for Harp (IV. Avalokiteshvara)",
            "trackid": "NjoPmiCrNIk"
        },
        "14": {
            "artist": "Lori Vambe",
            "ratio": 9,
            "title": "Drumsong (One)",
            "trackid": "qOdLLB4Bvak"
        },
        "15": {
            "artist": "Kronos Quartet Plays Terry Riley",
            "ratio": 7,
            "title": "IV. The Ecstasy- At The Summit",
            "trackid": "SJLNUrkYQd8"
        },
        "16": {
            "artist": "Hula Om",
            "ratio": 4,
            "title": "Raul Lovisoni & Francesco Messina",
            "trackid": "j5PHARU9QpQ"
        },
        "17": {
            "artist": "Roland P. Young",
            "ratio": 5,
            "title": "Late Afternoon Light (2015)",
            "trackid": "XwMP8DsR9tk"
        },
        "18": {
            "artist": "O Yuki Conjugate",
            "ratio": 9,
            "title": "Cloud Cover (Final Image, 1987)",
            "trackid": "Qryf55bHjdc"
        },
        "19": {
            "artist": "Mary Lattimore",
            "ratio": 9,
            "title": "The Warm Shoulder",
            "trackid": "XZTKo4qRTdA"
        },
        "20": {
            "artist": "Pete La Roca",
            "ratio": 9,
            "title": "Bliss",
            "trackid": "3pCF0-VSXAY"
        },
        "21": {
            "artist": "Maria Rita Stumpf",
            "ratio": 3,
            "title": "A Cidade (feat. Ricardo Bordini)",
            "trackid": "8D2g2JD_nWM"
        },
        "22": {
            "artist": "Ilias Pitsios",
            "ratio": 0,
            "title": "Vangelis Katsoulis - Longing",
            "trackid": "g39OqbYLmZo"
        },
        "23": {
            "artist": "Alice Coltrane",
            "ratio": 9,
            "title": "Rama Rama",
            "trackid": "-SAjt69KZmU"
        },
        "24": {
            "artist": "Claudine Chirac",
            "ratio": 9,
            "title": "Nautilus (1981)",
            "trackid": "piacl9G9GNs"
        },
        "25": {
            "artist": "Marion Brown",
            "ratio": 9,
            "title": "Sweet Earth Flying, Pt.1",
            "trackid": "niKhxl2zMoo"
        },
        "26": {
            "artist": "Prince",
            "ratio": 9,
            "title": "Epic Guitar Solo Compilation in 7 minutes",
            "trackid": "fnvV6z1J-KI"
        }
    },
    "mo-probs-20th-march-2017": {
        "00": {
            "artist": "Delia Derbyshire",
            "ratio": 9,
            "title": "Blue Veils and Golden Sands",
            "trackid": "kh86LtuuY4U"
        },
        "01": {
            "artist": "No Church In The Wild Explicit (feat. Frank Ocean & The",
            "ratio": 3,
            "title": "Dream)",
            "trackid": "FJt7gNi3Nr4"
        },
        "02": {
            "artist": "Georges Teperino",
            "ratio": 9,
            "title": "Cosmic Sounds N°3",
            "trackid": "xq35RH_iM3c"
        },
        "03": {
            "artist": "Johanna M. Beyer",
            "ratio": 9,
            "title": "Music Of The Spheres [1938]",
            "trackid": "_REVFN7A6_4"
        },
        "04": {
            "artist": "Piero Umiliani",
            "ratio": 9,
            "title": "État Hypnotique",
            "trackid": "_rxxXR9ER7o"
        },
        "05": {
            "artist": "Gail Laughton",
            "ratio": 9,
            "title": "Pompeii 76 A.D.",
            "trackid": "8pmNxgW2XEI"
        },
        "06": {
            "artist": "Zdeněk Liška",
            "ratio": 9,
            "title": "Song Of The Siren",
            "trackid": "8ocoT_fkzdk"
        },
        "07": {
            "artist": "Krzysztof Penderecki",
            "ratio": 9,
            "title": "Utrenja Ewangelia",
            "trackid": "2QLdbCQhzfI"
        },
        "08": {
            "artist": "Ennio Morricone",
            "ratio": 9,
            "title": "Pneuma",
            "trackid": "-RFbGayHJ60"
        },
        "09": {
            "artist": "Joe McPhee",
            "ratio": 9,
            "title": "Pablo Suicide",
            "trackid": "WmzPuNisYUY"
        },
        "10": {
            "artist": "Jacob Wilson",
            "ratio": 3,
            "title": "Derek Jarman The last of England and Godspeed You Black Emperor   East Hastings",
            "trackid": "YFAlWJF_dqM"
        },
        "11": {
            "artist": "AC/DC",
            "ratio": 3,
            "title": "Shoot To Thrill (Iron Man 2 Version)",
            "trackid": "xRQnJyP77tY"
        },
        "12": {
            "artist": "Classical Themes",
            "ratio": 5,
            "title": "A Clockwork Orange (Vinyl)",
            "trackid": "x1bWojIwR8s"
        },
        "13": {
            "artist": "Luciann Hjorth",
            "ratio": 5,
            "title": "Springtime",
            "trackid": "EHnr9anTqEk"
        },
        "14": {
            "artist": "John Paul Jones",
            "ratio": 9,
            "title": "4 Minute Warning",
            "trackid": "zZGQf6eyOVg"
        },
        "15": {
            "artist": "Roland Ramakistin",
            "ratio": 3,
            "title": "Je t'aime, je t'aime",
            "trackid": "Pu5her0pPUw"
        },
        "16": {
            "artist": "Deux Filles",
            "ratio": 9,
            "title": "L'Intrigue (1984)",
            "trackid": "y8nhEoT5ON8"
        },
        "17": {
            "artist": "Nuno Canavarro",
            "ratio": 9,
            "title": "Untitled (1988)",
            "trackid": "4RHVq98KUJ4"
        },
        "18": {
            "artist": "Elodie Lauten",
            "ratio": 9,
            "title": "Vision",
            "trackid": "QTNv4eYsH-I"
        },
        "19": {
            "artist": "Lol Coxhill & Morgan Fisher",
            "ratio": 9,
            "title": "Matt Finish",
            "trackid": "1MXTDe-kAZc"
        },
        "20": {
            "artist": "Steve Roach",
            "ratio": 9,
            "title": "Comeback (Now, 1982)",
            "trackid": "j9oZUaQqEe0"
        },
        "21": {
            "artist": "Mica Levi & Oliver Coates",
            "ratio": 9,
            "title": "Pre-Barok (2016)",
            "trackid": "32FnOUxAkmk"
        },
        "22": {
            "artist": "John Cage",
            "ratio": 9,
            "title": "In A Landscape",
            "trackid": "PSmXAG2mYY4"
        },
        "23": {
            "artist": "picnicatlicklerock",
            "ratio": 3,
            "title": "the khan jamal creative arts ensemble   breath of life   drum dance to the motherland",
            "trackid": "QoYQn86CL9I"
        },
        "24": {
            "artist": "Joe McPhee",
            "ratio": 9,
            "title": "Cosmic Love Organ Alone",
            "trackid": "rvrTfrJQ5ws"
        },
        "25": {
            "artist": "Phonophobia",
            "ratio": 9,
            "title": "Instrumental",
            "trackid": "W1DrHif1ors"
        },
        "26": {
            "artist": "Find Random Money",
            "ratio": 3,
            "title": "Powerful Subliminal- 💰🤑💸 (listen as needed !)",
            "trackid": "QK8w6IDjQIQ"
        },
        "27": {
            "artist": "Harold Budd",
            "ratio": 9,
            "title": "The Whispers",
            "trackid": "Fzm74jVr0Fs"
        },
        "28": {
            "artist": "This Mortal Coil",
            "ratio": 9,
            "title": "Barramundi",
            "trackid": "peX3i4yW_3s"
        },
        "29": {
            "artist": "Sarah Davachi",
            "ratio": 4,
            "title": "Alas, Departing",
            "trackid": "e6QUKsEezGw"
        },
        "30": {
            "artist": "Coil",
            "ratio": 9,
            "title": "The Mothership And The Fatherland (Part 2)",
            "trackid": "o96M_Wiy9Oc"
        },
        "31": {
            "artist": "Chris and Cosey",
            "ratio": 9,
            "title": "Moving Still",
            "trackid": "woJcMaTAXnI"
        },
        "32": {
            "artist": "Cocteau Twins",
            "ratio": 9,
            "title": "Cherry Coloured Funk",
            "trackid": "hWTAHYCKpFc"
        }
    },
    "mo-probs-23rd-january-2017": {
        "00": {
            "artist": "Spectre",
            "ratio": 9,
            "title": "- Krush (Bloody Dub Mix) 5-10",
            "trackid": "wiDe4wmxJQU"
        },
        "01": {
            "artist": "[1993] dynamic wave",
            "ratio": 9,
            "title": "krygenic",
            "trackid": "WWb_X8wD19k"
        },
        "02": {
            "artist": "Gescom",
            "ratio": 9,
            "title": "Cicada (1994)",
            "trackid": "g775Zb-FQLw"
        },
        "03": {
            "artist": "Stasis ‎",
            "ratio": 9,
            "title": "Point Of No Return",
            "trackid": "yMXz8O5acac"
        },
        "04": {
            "artist": "Tony Evans",
            "ratio": 4,
            "title": "How to Have Strength in Your Struggles | Tony Evans Sermon",
            "trackid": "D8A26qdp3Yk"
        },
        "05": {
            "artist": "Model 500",
            "ratio": 9,
            "title": "Pick Up The Flow",
            "trackid": "lP53ypyiqyM"
        },
        "06": {
            "artist": "A Guy Called Gerald",
            "ratio": 9,
            "title": "Pacific Samba",
            "trackid": "B-a3pIwkIOo"
        },
        "07": {
            "artist": "Callisto",
            "ratio": 9,
            "title": "Ambent II",
            "trackid": "9Xi0EUTHkZE"
        },
        "08": {
            "artist": "Callisto",
            "ratio": 9,
            "title": "Jungle I",
            "trackid": "y6F5mPZNTXI"
        },
        "09": {
            "artist": "Project A",
            "ratio": 9,
            "title": "KO - Afterglow Pt 1 & 2 [1994]",
            "trackid": "27BdhBWjRjk"
        },
        "10": {
            "artist": "BFC",
            "ratio": 9,
            "title": "It's A Shame",
            "trackid": "ipJdiNu6kh4"
        },
        "11": {
            "artist": "Shirley & Company",
            "ratio": 4,
            "title": "Shame. Shame, Shame",
            "trackid": "U0mjlDDk3tE"
        },
        "12": {
            "artist": "Acetylcholine",
            "ratio": 9,
            "title": "DjStingray 313",
            "trackid": "kbx_pJ_Pg7M"
        },
        "13": {
            "artist": "BFC aka Carl Craig",
            "ratio": 9,
            "title": "Galaxy",
            "trackid": "itRkCXJh_Sw"
        },
        "14": {
            "artist": "Demdike Stare",
            "ratio": 9,
            "title": "Rathe",
            "trackid": "ZlCUkv2VxJs"
        },
        "15": {
            "artist": "DJ GUY",
            "ratio": 9,
            "title": "Black & White (1995)",
            "trackid": "paOXUQNNvY0"
        },
        "16": {
            "artist": "Goldie & 4 Hero (Internal Affairs)",
            "ratio": 9,
            "title": "Shinin' Down On Me",
            "trackid": "ElnKK9HCfoI"
        },
        "17": {
            "artist": "Fugue",
            "ratio": 9,
            "title": "Contrapoint",
            "trackid": "F7H69NFVibM"
        },
        "18": {
            "artist": "Kenny Larkin",
            "ratio": 9,
            "title": "Tedra (1994)",
            "trackid": "l8EaoGwNDfA"
        },
        "19": {
            "artist": "Aksak Maboul",
            "ratio": 9,
            "title": "Scratch Holiday",
            "trackid": "daeQY7EDP-k"
        },
        "20": {
            "artist": "Funkadelic",
            "ratio": 9,
            "title": "Eulogy And Light Lyrics",
            "trackid": "AMtIcqUVCbk"
        }
    },
    "mo-probs-23rd-june-2017": {
        "00": {
            "artist": "Hailu Mergia",
            "ratio": 9,
            "title": "Ambasel",
            "trackid": "ktCEHgDc3zI"
        },
        "01": {
            "artist": "Dalton",
            "ratio": 9,
            "title": "Soul Brother",
            "trackid": "4CBbxH-Vm_s"
        },
        "02": {
            "artist": "Seelenluft",
            "ratio": 9,
            "title": "Manila (official Video)",
            "trackid": "mh2SiGuDT1A"
        },
        "03": {
            "artist": "Yussef Kamaal",
            "ratio": 9,
            "title": "Yo Chavez (from the album Black Focus)",
            "trackid": "RkIn4bHp6Pc"
        },
        "04": {
            "artist": "Gary Wilson",
            "ratio": 9,
            "title": "You Think You Really KNow Me",
            "trackid": "h7O9S95yyA8"
        },
        "05": {
            "artist": "G Perico",
            "ratio": 9,
            "title": "My World",
            "trackid": "RF1svvSROZ8"
        },
        "06": {
            "artist": "Sa",
            "ratio": 7,
            "title": "Ra Creative Partners - The Bone Song",
            "trackid": "gEwIBjDMIVw"
        },
        "07": {
            "artist": "Isaiah Rashad",
            "ratio": 9,
            "title": "Free Lunch",
            "trackid": "QJksTRgY8-c"
        },
        "08": {
            "artist": "Budgie",
            "ratio": 9,
            "title": "Confession",
            "trackid": "zOpcUpoVozc"
        },
        "09": {
            "artist": "Jazmine Sullivan",
            "ratio": 9,
            "title": "Let It Burn",
            "trackid": "2EATQP3_fFg"
        },
        "10": {
            "artist": "Isaiah Rashad",
            "ratio": 9,
            "title": "Stuck In The Mud (feat. SZA)",
            "trackid": "tV7Uab1ITok"
        },
        "11": {
            "artist": "Pedestrian One",
            "ratio": 0,
            "title": "Body In Movement",
            "trackid": "Kwbq2ezeGu8"
        },
        "12": {
            "artist": "Kwesachu (feat. Tirzah)",
            "ratio": 9,
            "title": "Nothing",
            "trackid": "J0-9jXz0ALE"
        },
        "13": {
            "artist": "Laurel Halo",
            "ratio": 9,
            "title": "Moontalk",
            "trackid": "hbimvNPgryI"
        },
        "14": {
            "artist": "",
            "ratio": -1,
            "title": "",
            "trackid": ""
        },
        "15": {
            "artist": "Frank Ocean",
            "ratio": 9,
            "title": "Biking V4 (Ft. Jay-Z, Frank's Solo Verse, and Tyler, The Creator with HQ Ending)",
            "trackid": "TtCLhPsEidQ"
        },
        "16": {
            "artist": "Flying Lotus",
            "ratio": 9,
            "title": "Camel",
            "trackid": "t6SXXx1Fu_4"
        },
        "17": {
            "artist": "Selina Macias",
            "ratio": 5,
            "title": "\"Hiatus (Waiting)\" by Ravyn Lenae| Choreography| @afrogyps",
            "trackid": "HtCUmwUXHQg"
        },
        "18": {
            "artist": "SZA",
            "ratio": 9,
            "title": "Love Galore (Lyrics) ft. Travis Scott",
            "trackid": "0mrPzjXlE5g"
        },
        "19": {
            "artist": "Bryson Tiller",
            "ratio": 9,
            "title": "No Longer Friends (True To Self)",
            "trackid": "gpLf36ZsJQY"
        },
        "20": {
            "artist": "SZA",
            "ratio": 9,
            "title": "Broken Clocks (Official Audio)",
            "trackid": "0Exxu8lsGYE"
        },
        "21": {
            "artist": "Moodymann",
            "ratio": 7,
            "title": "Lyk U Use 2 (feat. Stress)",
            "trackid": "z_trFeBXW5c"
        },
        "22": {
            "artist": "Samsonyte",
            "ratio": 8,
            "title": "Lucy (feat. ScottyMay)",
            "trackid": "bCZUW1sI_DU"
        },
        "23": {
            "artist": "Thundercat",
            "ratio": 9,
            "title": "Them Changes",
            "trackid": "GNCd_ERZvZM"
        },
        "24": {
            "artist": "Lonnie Liston Smith",
            "ratio": 9,
            "title": "Summer Nights",
            "trackid": "xCzItYd3bW4"
        },
        "25": {
            "artist": "Miles Davis",
            "ratio": 9,
            "title": "Selim (1971)",
            "trackid": "Br_ZBl7ve2U"
        },
        "26": {
            "artist": "The Isley Brothers",
            "ratio": 9,
            "title": "The Highways Of My Life FULL HD (lyrics) 1973",
            "trackid": "sC9qKo2y5bg"
        },
        "27": {
            "artist": "Ponderosa Twins Plus One",
            "ratio": 9,
            "title": "Bound",
            "trackid": "d6mGHwHMB5s"
        },
        "28": {
            "artist": "Kanye West",
            "ratio": 9,
            "title": "Everything I am (Official Instrumental HQ)",
            "trackid": "_x4Oz7C8WFk"
        },
        "29": {
            "artist": "Funkadelic",
            "ratio": 9,
            "title": "Eulogy And Light Lyrics",
            "trackid": "AMtIcqUVCbk"
        },
        "30": {
            "artist": "Frank Ocean",
            "ratio": 9,
            "title": "Godspeed",
            "trackid": "P18g4rKns6Q"
        },
        "31": {
            "artist": "Frank Ocean",
            "ratio": 9,
            "title": "Seigfried",
            "trackid": "RWgpBlz16-s"
        },
        "32": {
            "artist": "Mica Levi",
            "ratio": 9,
            "title": "Love",
            "trackid": "Z_Cc20I-maM"
        }
    },
    "mo-probs-29th-december-2016": {
        "00": {
            "artist": "Pale Cocoon",
            "ratio": 9,
            "title": "Sora",
            "trackid": "8Xu7R2D6zTw"
        },
        "01": {
            "artist": "Woo",
            "ratio": 9,
            "title": "A Wave",
            "trackid": "XjBJj4dOVLM"
        },
        "02": {
            "artist": "Hawaii Volcanoes",
            "ratio": 9,
            "title": "Palm",
            "trackid": "aklLudW_fYs"
        },
        "03": {
            "artist": "Lady June",
            "ratio": 9,
            "title": "Tunion.",
            "trackid": "w6hJmbvgo3Q"
        },
        "04": {
            "artist": "Zinthetyzer",
            "ratio": 9,
            "title": "Green Onions (1982)",
            "trackid": "7FZRegJ4KWg"
        },
        "05": {
            "artist": "La Tête À L'Envers Et Ses Malentendus",
            "ratio": 9,
            "title": "Glop Pas Glop",
            "trackid": "XCyFlO1Szlo"
        },
        "06": {
            "artist": "Brenda and The Beach Balls",
            "ratio": 9,
            "title": "Theme From A Tall Dark Stranger",
            "trackid": "DOxJWggImL8"
        },
        "07": {
            "artist": "Sensations' Fix",
            "ratio": 9,
            "title": "Dark Side of Religion",
            "trackid": "Xzy90-v0lf8"
        },
        "08": {
            "artist": "Jon Hassell",
            "ratio": 9,
            "title": "Empire iii",
            "trackid": "s-Zd0E4nXw4"
        },
        "09": {
            "artist": "Pharoah Sanders",
            "ratio": 9,
            "title": "\"High Life\"",
            "trackid": "9zbKjU5te2k"
        },
        "10": {
            "artist": "REME & Henry Jacobs",
            "ratio": 3,
            "title": "Equal Rites",
            "trackid": "nJseAC7RXQw"
        },
        "11": {
            "artist": "Heckle & Jeckle",
            "ratio": 4,
            "title": "La mutinerie (Acid Pirate 18)",
            "trackid": "BAiyaImANGw"
        },
        "12": {
            "artist": "VANDORENTV",
            "ratio": 4,
            "title": "Edison Clarinet Quartet playing \"Ouragan\" by Patrice Sciortino",
            "trackid": "NYQ5Du2qDFI"
        },
        "13": {
            "artist": "A 40s song with two 40s tubas",
            "ratio": 3,
            "title": "It's Been a Long Long Time, Harry James and Kitty Kallen",
            "trackid": "UWdvg9fsikY"
        },
        "14": {
            "artist": "Haruomi Hosono",
            "ratio": 3,
            "title": "Philharmony - 04 - Platonic",
            "trackid": "ODbEAS_-cpY"
        },
        "15": {
            "artist": "Ichiko Hashimoto",
            "ratio": 9,
            "title": "Kitsune",
            "trackid": "UELvVDDXEG0"
        },
        "16": {
            "artist": "SES",
            "ratio": 3,
            "title": "A Chamuscada",
            "trackid": "WLjAhMJD7FM"
        },
        "17": {
            "artist": "Seigen Ono",
            "ratio": 9,
            "title": "Mallets",
            "trackid": "cyjoYs-7HDk"
        },
        "18": {
            "artist": "Inoyamaland",
            "ratio": 9,
            "title": "Collecting Net",
            "trackid": "O3qLDiLEK2s"
        },
        "19": {
            "artist": "Eitetsu Hayashi (林英哲)",
            "ratio": 9,
            "title": "Karabinka (カラビンカ)",
            "trackid": "2kQQxiNeVcY"
        },
        "20": {
            "artist": "Taeko Ohnuki",
            "ratio": 9,
            "title": "Inori (1983)",
            "trackid": "U2A4toBXVLA"
        },
        "21": {
            "artist": "五つの赤い風船 [itsutsu no akai fusen]",
            "ratio": 3,
            "title": "new sky- part 1 (1971)",
            "trackid": "X7S7SBRvo6A"
        },
        "22": {
            "artist": "Suso Sáiz",
            "ratio": 9,
            "title": "Prefiero El Naranja",
            "trackid": "RRkCjCkoa7k"
        },
        "23": {
            "artist": "Mica Levi & Oliver Coates",
            "ratio": 9,
            "title": "Pre-Barok (2016)",
            "trackid": "32FnOUxAkmk"
        },
        "24": {
            "artist": "Mica Levi & Oliver Coates  \"Barok Main\"",
            "ratio": 3,
            "title": "Boiler Room Debuts",
            "trackid": "3Hf8S0XjRAw"
        },
        "25": {
            "artist": "Laura Allan",
            "ratio": 9,
            "title": "Waterfall",
            "trackid": "sCEu2_4ZyMI"
        },
        "26": {
            "artist": "Roberto Cacciapaglia",
            "ratio": 9,
            "title": "3rd Movement (1975)",
            "trackid": "Ys4e7W546xg"
        },
        "27": {
            "artist": "John Cage",
            "ratio": 9,
            "title": "Imaginary Landscape No  5 (1952)",
            "trackid": "bu38ZidvmEY"
        },
        "28": {
            "artist": "Tyondai Braxton's HIVE",
            "ratio": 5,
            "title": "Live at The Kitchen — \"Boids\"",
            "trackid": "mWRaR4_yxYQ"
        },
        "29": {
            "artist": "Most Emotional OST",
            "ratio": 4,
            "title": "Moonlit Night - \"Death Parade\" - デス・パレード OST",
            "trackid": "ewBOcdz29Sw"
        }
    },
    "mo-probs-5th-april-2017": {
        "00": {
            "artist": "Octave One",
            "ratio": 9,
            "title": "Cosmic Surf",
            "trackid": "YygJTdFZQAU"
        },
        "01": {
            "artist": "UnknownmiX",
            "ratio": 9,
            "title": "Japanese Funk Machine",
            "trackid": "gd2yg8y2vNU"
        },
        "02": {
            "artist": "Tomoko Aran",
            "ratio": 9,
            "title": "Hannya",
            "trackid": "17OeCznSm5I"
        },
        "03": {
            "artist": "Blowback",
            "ratio": 5,
            "title": "Black Hole",
            "trackid": "wIQNzRWp5ks"
        },
        "04": {
            "artist": "Dante Klein",
            "ratio": 4,
            "title": "what i like about u",
            "trackid": "XehlywgmwQ0"
        },
        "05": {
            "artist": "Busta Rhymes",
            "ratio": 9,
            "title": "Everything Remains Raw",
            "trackid": "q0lin0VDi6w"
        },
        "06": {
            "artist": "Psyche/BFC",
            "ratio": 5,
            "title": "Neurotic Behavior",
            "trackid": "F7GGIdq2h1o"
        },
        "07": {
            "artist": "Drexciya",
            "ratio": 9,
            "title": "Soul Of The Sea",
            "trackid": "xABjcnLjhVA"
        },
        "08": {
            "artist": "GEMINI",
            "ratio": 9,
            "title": "Phosphorscene",
            "trackid": "AxzpPcfacz0"
        },
        "09": {
            "artist": "K. Alexi Shelby",
            "ratio": 9,
            "title": "Vertigo (original mix) (1989)",
            "trackid": "dhXurmogXus"
        },
        "10": {
            "artist": "Octave One",
            "ratio": 9,
            "title": "\"Seige\"",
            "trackid": "EnZfX8-Whtw"
        },
        "11": {
            "artist": "Ted Milton",
            "ratio": 9,
            "title": "Love Is Like A Violence",
            "trackid": "yCKCtyRpf84"
        },
        "12": {
            "artist": "Lizzy Mercier Descloux",
            "ratio": 9,
            "title": "Hard-boiled Babe",
            "trackid": "HpWl_IsPneI"
        },
        "13": {
            "artist": "Dinosaur L",
            "ratio": 9,
            "title": "Clean On Your Bean #1",
            "trackid": "XpgoF9-F4tc"
        }
    },
    "mo-probs-8th-march-2018": {
        "00": {
            "artist": "Skrillex",
            "ratio": 4,
            "title": "First of the Year (Equinox)",
            "trackid": "2cXDgFwE13g"
        },
        "01": {
            "artist": "naminohanawreck",
            "ratio": 3,
            "title": "ureii",
            "trackid": "LeLHM5Q6iuE"
        },
        "02": {
            "artist": "Pupajim",
            "ratio": 9,
            "title": "U.F.O (MAFFI/JAHTARI)",
            "trackid": "bCc_vWARWTA"
        },
        "03": {
            "artist": "Sun Ra & His Arkestra",
            "ratio": 9,
            "title": "My Brother the Wind",
            "trackid": "jB-NNNe1318"
        },
        "04": {
            "artist": "STILL",
            "ratio": 9,
            "title": "Mangrovia (PAN 80)",
            "trackid": "8BLrCP7Rufg"
        },
        "05": {
            "artist": "Woody Noble",
            "ratio": 9,
            "title": "Love Is So Good",
            "trackid": "uVjypQFrbD0"
        },
        "06": {
            "artist": "Xanadu & Sweet Lady",
            "ratio": 9,
            "title": "Rocker's Choice",
            "trackid": "FrJpw9Hs_DM"
        },
        "07": {
            "artist": "Cloud One",
            "ratio": 9,
            "title": "Cloud One Patty Duke (Instrumental - Part 1)",
            "trackid": "UfJPQrKyYXk"
        },
        "08": {
            "artist": "Norman Riley",
            "ratio": 9,
            "title": "Sounds of the Streets",
            "trackid": "a9f8U6MdCcY"
        },
        "09": {
            "artist": "Nina Simone",
            "ratio": 9,
            "title": "Funkier Than A Mosquito's Tweeter (Jazzeem's All Styles Remix)",
            "trackid": "L4SGc7IbgCU"
        },
        "10": {
            "artist": "Cedric Im Brooks & The Light of Saba",
            "ratio": 9,
            "title": "Sabasi",
            "trackid": "YC2Ny0ka15U"
        },
        "11": {
            "artist": "UnknownmiX",
            "ratio": 9,
            "title": "Django",
            "trackid": "MzP0JhU95E0"
        },
        "12": {
            "artist": "Hallucinator",
            "ratio": 9,
            "title": "Sethos",
            "trackid": "ngL6d9ZvKWk"
        },
        "13": {
            "artist": "Aamina Camaari",
            "ratio": 9,
            "title": "Rag Waa Nacab Iyo Nasteexo",
            "trackid": "DdQSxK_ukrk"
        }
    },
    "uniqlo-tatelates-mo-probs-28th-july-2017": {
        "00": {
            "artist": "Pitbull",
            "ratio": 0,
            "title": "Timber (Official Video) (feat. Kesha)",
            "trackid": "hHUbLv4ThOo"
        },
        "01": {
            "artist": "Andrea Belfi ‎",
            "ratio": 9,
            "title": "Roteano",
            "trackid": "-p-C9h25wzo"
        },
        "02": {
            "artist": "Eminem",
            "ratio": 3,
            "title": "From The D 2 The LBC",
            "trackid": "RjrA-slMoZ4"
        },
        "03": {
            "artist": "Tyondai Braxton's HIVE",
            "ratio": 5,
            "title": "Live at The Kitchen — \"Boids\"",
            "trackid": "mWRaR4_yxYQ"
        },
        "04": {
            "artist": "Cevdet Erek",
            "ratio": 9,
            "title": "Heal",
            "trackid": "j1L7Y6-VbIk"
        },
        "05": {
            "artist": "SUGAI KEN",
            "ratio": 9,
            "title": "Utsuo No Maigiri",
            "trackid": "YuLx1ldZgQA"
        },
        "06": {
            "artist": "Masayoshi Fujita & Jan Jelinek",
            "ratio": 9,
            "title": "Helio",
            "trackid": "pnjNk3jPcG0"
        },
        "07": {
            "artist": "Masayoshi Fujita & Jan Jelinek",
            "ratio": 9,
            "title": "Vague, Yet (2016)",
            "trackid": "64sbo75N7FA"
        },
        "08": {
            "artist": "Ben Vida",
            "ratio": 9,
            "title": "Ssseeeeiiiii",
            "trackid": "S1ioNMHgoKE"
        }
    }
}