{
    "jane-remover-15th-september-2023": {
        "00": {
            "s0": "",
            "s1": [
                {
                    "artist": "Jane Remover",
                    "title": "Lips",
                    "uri": "05SEi2EuY93D6UHHUSNZGc"
                },
                {
                    "artist": "Jane Remover",
                    "title": "how to lie",
                    "uri": "3mPk0eckjHFr7Q6L0M8dt9"
                },
                {
                    "artist": "Jane Remover",
                    "title": "movies for guys",
                    "uri": "1urgZoAjz91vFqPEokA1OR"
                }
            ]
        },
        "01": {
            "s0": [
                {
                    "artist": "Carly Rae Jepsen",
                    "title": "Talking to Yourself",
                    "uri": "7I7Dk8FOkZqhqZp9N2RKiP"
                },
                {
                    "artist": "Carly Rae Jepsen",
                    "title": "Talking to Yourself",
                    "uri": "4YtsVmEEaptzgX6uoTBpCl"
                },
                {
                    "artist": "Carly Rae Jepsen",
                    "title": "Talking to Yourself",
                    "uri": "02qgkoUBtCzTM1IUXQ1dMC"
                }
            ],
            "s1": [
                {
                    "artist": "Carly Rae Jepsen",
                    "title": "Talking to Yourself",
                    "uri": "7I7Dk8FOkZqhqZp9N2RKiP"
                },
                {
                    "artist": "Carly Rae Jepsen",
                    "title": "Run Away With Me",
                    "uri": "0FS7B5o3QyvOD8eWjnbLoO"
                },
                {
                    "artist": "Carly Rae Jepsen",
                    "title": "I Really Like You",
                    "uri": "2hHLbkatPwOOmrNxTiD41L"
                }
            ]
        },
        "02": {
            "s0": "",
            "s1": [
                {
                    "artist": "SOPHIE",
                    "title": "Faceshopping",
                    "uri": "2rN1ODOsaNfYu782rw36jR"
                },
                {
                    "artist": "SOPHIE",
                    "title": "Not Okay - Alone Mix",
                    "uri": "57aGMQ5ZOSWIAf4n0fYEnt"
                },
                {
                    "artist": "Sophie Ellis-Bextor",
                    "title": "Get Over You",
                    "uri": "0r8U4M18cn9WGWWlVIfQ7i"
                }
            ]
        },
        "03": {
            "s0": "",
            "s1": [
                {
                    "artist": "Bar9",
                    "title": "Piano Tune",
                    "uri": "7nmdmrJFiIDj8L5sINCUQQ"
                },
                {
                    "artist": "Peppertune",
                    "title": "Float",
                    "uri": "6xHxN9kY5EUjEo1160pnMl"
                },
                {
                    "artist": "BARO",
                    "title": "İSTANBUL",
                    "uri": "5EJQMvBbVVIFJkDb9J3fu3"
                }
            ]
        },
        "04": {
            "s0": "",
            "s1": [
                {
                    "artist": "Hatfield & The North",
                    "title": "Going Up To People And Tinkling",
                    "uri": "0Y96JrNGuhHlZJMoMa8gUK"
                },
                {
                    "artist": "Xandl",
                    "title": "The Reason - Radio Edit",
                    "uri": "5KThtMIv1xANYdpvhVHKEx"
                },
                {
                    "artist": "Harfordrdtay",
                    "title": "Freestyle",
                    "uri": "5UPVQTTMjzwP0A1k2rEAIB"
                }
            ]
        },
        "05": {
            "s0": "",
            "s1": [
                {
                    "artist": "Jane Remover",
                    "title": "goldfish",
                    "uri": "7A8YnjMhMrTfVqMRRfayv7"
                },
                {
                    "artist": "Jane Remover",
                    "title": "pretender",
                    "uri": "44auFUrGECh2dOIWHyGZyl"
                },
                {
                    "artist": "Jane Remover",
                    "title": "movies for guys",
                    "uri": "1urgZoAjz91vFqPEokA1OR"
                }
            ]
        },
        "06": {
            "s0": "",
            "s1": [
                {
                    "artist": "underscores",
                    "title": "You don't even know who I am",
                    "uri": "6ClqRD9uFMj4VD8GuSr7mG"
                },
                {
                    "artist": "underscores",
                    "title": "You don't even know who I am",
                    "uri": "17BgCZrJKTBY9Z9A7dJAaa"
                },
                {
                    "artist": "Pop Talk",
                    "title": "You Don't Even Know Me Now",
                    "uri": "47gLTYb2DYcNIxMqxPMYut"
                }
            ]
        },
        "07": {
            "s0": "",
            "s1": [
                {
                    "artist": "Ryan Beatty",
                    "title": "White Teeth - Live Performance",
                    "uri": "4vD1vb8wlLVtweYK67Praf"
                },
                {
                    "artist": "Ryan Beatty",
                    "title": "Andromeda",
                    "uri": "5Br4bQG5MwYZTKpFfiw4no"
                },
                {
                    "artist": "Ryan Beatty",
                    "title": "Ribbons",
                    "uri": "1mn1vm47Qm3h91kgNRmXf0"
                }
            ]
        },
        "08": {
            "s0": "",
            "s1": [
                {
                    "artist": "Mariah Carey",
                    "title": "Vanishing",
                    "uri": "6PP8I9FUWPIVRvV81anBnR"
                },
                {
                    "artist": "fam0uz",
                    "title": "Vanished - Slowed",
                    "uri": "3QiT3AwJFczfpRnYrx9Z0J"
                },
                {
                    "artist": "Crystal Castles",
                    "title": "Vanished",
                    "uri": "3gGMsx3jxYKfhXq8LMj1tz"
                }
            ]
        },
        "09": {
            "s0": [
                {
                    "artist": "Liz Phair",
                    "title": "Polyester Bride",
                    "uri": "3Tbs9O6zy07BjjCU1omonJ"
                },
                {
                    "artist": "Liz Phair",
                    "title": "Polyester Bride - Girly-Sound Version",
                    "uri": "2T70mNgnmtGG2uU1IfH73Q"
                },
                {
                    "artist": "Liz Phair",
                    "title": "Polyester Bride - Girly-Sound Version",
                    "uri": "1TAVqhzsIYqbFVzrHncSGe"
                }
            ],
            "s1": [
                {
                    "artist": "Liz Phair",
                    "title": "Polyester Bride",
                    "uri": "3Tbs9O6zy07BjjCU1omonJ"
                },
                {
                    "artist": "Liz Phair",
                    "title": "Fuck and Run - 2018 Remaster",
                    "uri": "2qpmugEb0DI8kZLszkBLBT"
                },
                {
                    "artist": "Liz Phair",
                    "title": "Why Can't I?",
                    "uri": "4z4PB23xYTg1oANmyZovsw"
                }
            ]
        },
        "10": {
            "s0": "",
            "s1": [
                {
                    "artist": "Jane Remover",
                    "title": "your clothes",
                    "uri": "5gFfE8UgFslvqjVQw7dktZ"
                },
                {
                    "artist": "Jane Weaver",
                    "title": "Lux",
                    "uri": "5cpe7ADi7m36UwUVK7KHRS"
                },
                {
                    "artist": "JanRevolution",
                    "title": "Man Without Return",
                    "uri": "1ZG9t1NWQl1aHZ3QKeCBGR"
                }
            ]
        }
    },
    "jane-remover-18th-august-2023": {
        "00": {
            "s0": "",
            "s1": [
                {
                    "artist": "Jane Remover",
                    "title": "Lips",
                    "uri": "05SEi2EuY93D6UHHUSNZGc"
                },
                {
                    "artist": "Jane Remover",
                    "title": "homeswitcher",
                    "uri": "3wGDs4CbpDqpsTYyN5pe8o"
                },
                {
                    "artist": "Jane Detour",
                    "title": "Micro Virusem",
                    "uri": "1XgcoQ40YKECeRPAU6mWLw"
                }
            ]
        }
    },
    "jane-remover-21st-july-2023": {
        "00": {
            "s0": "",
            "s1": ""
        },
        "01": {
            "s0": "",
            "s1": ""
        },
        "02": {
            "s0": "",
            "s1": [
                {
                    "artist": "Talib4n",
                    "title": "JACK MY SWAG",
                    "uri": "5QqumIQ8qVTsBGocXl7V56"
                },
                {
                    "artist": "T5",
                    "title": "My Swag (feat. Minx)",
                    "uri": "5FI0OJI9MsvmwW2egKpJXb"
                },
                {
                    "artist": "Leroy Brown Beatz On Da Track",
                    "title": "Myself",
                    "uri": "7KECQFS3HHIaKfUGUlayYe"
                }
            ]
        },
        "03": {
            "s0": "",
            "s1": [
                {
                    "artist": "Levent Geiger",
                    "title": "It's Up to Me",
                    "uri": "1CP8ecZCpLn8y3ib2UEHir"
                },
                {
                    "artist": "knoodle",
                    "title": "It’s only Up to You",
                    "uri": "3yA45GRs4io5DncCWm4isa"
                },
                {
                    "artist": "Eikichi Yazawa",
                    "title": "IT'S UP TO YOU! - Remastered 2022",
                    "uri": "6cRoFHRVFx07WzdK7vdhFs"
                }
            ]
        },
        "04": {
            "s0": "",
            "s1": [
                {
                    "artist": "Cyril M",
                    "title": "Put Me Back Together",
                    "uri": "1y3JPDwWtrCA3fAYiMMTIB"
                },
                {
                    "artist": "Grace Grundy",
                    "title": "Put Me Back Together",
                    "uri": "0Qru5HaAItu3d4tJ686Sur"
                },
                {
                    "artist": "Cheat Codes",
                    "title": "Put Me Back Together (feat. Kiiara)",
                    "uri": "5BgsAQnzQFlunJY5T4k1Pd"
                }
            ]
        },
        "05": {
            "s0": "",
            "s1": [
                {
                    "artist": "bliss05",
                    "title": "i can't feel a thing",
                    "uri": "3hvO8G3fjrlstBgVK8pV0C"
                },
                {
                    "artist": "beetyl",
                    "title": "I Can't Feel a Thing",
                    "uri": "0CayikTJ5daCTMdVJhAgUs"
                }
            ]
        },
        "06": {
            "s0": "",
            "s1": [
                {
                    "artist": "Ella Fitzgerald",
                    "title": "I've Got A Crush On You",
                    "uri": "5DIVWgTeJ2fPIxaY9e7ZKn"
                },
                {
                    "artist": "Steve Tyrell",
                    "title": "I've Got a Crush On You",
                    "uri": "0Kp6wskdOWA5U74pbtZ3qQ"
                },
                {
                    "artist": "Hunter Paige",
                    "title": "i've got a crush on you",
                    "uri": "79S9Ea6Q347UAPTIWnLmV2"
                }
            ]
        },
        "07": {
            "s0": "",
            "s1": [
                {
                    "artist": "Wontolla",
                    "title": "Crush Depth",
                    "uri": "6b0vetGSc6FG6EwosXsXSf"
                },
                {
                    "artist": "Bellorum",
                    "title": "CRUSH",
                    "uri": "3l5KAvmMw41kdoU4lZZHVJ"
                },
                {
                    "artist": "Dixie",
                    "title": "Crush",
                    "uri": "3IsrHAkYqpJvr8UMAzGul9"
                }
            ]
        },
        "08": {
            "s0": "",
            "s1": ""
        },
        "09": {
            "s0": "",
            "s1": [
                {
                    "artist": "Queen",
                    "title": "Bring Back That Leroy Brown - Remastered 2011",
                    "uri": "5jQGIcVqaRqpaNkkFt4P8H"
                },
                {
                    "artist": "Leroy",
                    "title": "Six Days",
                    "uri": "7MNhOk0hRcmZUN6vHBUUPn"
                },
                {
                    "artist": "HeadCat",
                    "title": "Let It Rock",
                    "uri": "42grnqupsor2Y8YWLJ1kTR"
                }
            ]
        },
        "10": {
            "s0": "",
            "s1": ""
        },
        "11": {
            "s0": "",
            "s1": ""
        }
    },
    "jane-remover-23rd-june-2023": {
        "00": {
            "s0": "",
            "s1": [
                {
                    "artist": "Jane Remover",
                    "title": "pretender",
                    "uri": "44auFUrGECh2dOIWHyGZyl"
                },
                {
                    "artist": "Jane Remover",
                    "title": "goldfish",
                    "uri": "7A8YnjMhMrTfVqMRRfayv7"
                },
                {
                    "artist": "Jane Remover",
                    "title": "search party",
                    "uri": "490NAHwXWtwve0t4J2Q0D0"
                }
            ]
        },
        "01": {
            "s0": "",
            "s1": [
                {
                    "artist": "Jane Remover",
                    "title": "pretender",
                    "uri": "44auFUrGECh2dOIWHyGZyl"
                },
                {
                    "artist": "Jane Remover",
                    "title": "how to lie",
                    "uri": "3mPk0eckjHFr7Q6L0M8dt9"
                },
                {
                    "artist": "Jane Remover",
                    "title": "buzzcut, daisy",
                    "uri": "1IHWMSs40XqfjcEc5JN9UQ"
                }
            ]
        },
        "02": {
            "s0": "",
            "s1": [
                {
                    "artist": "Jane Remover",
                    "title": "search party",
                    "uri": "490NAHwXWtwve0t4J2Q0D0"
                },
                {
                    "artist": "Jane Remover",
                    "title": "goldfish",
                    "uri": "7A8YnjMhMrTfVqMRRfayv7"
                },
                {
                    "artist": "Jane Remover",
                    "title": "pretender",
                    "uri": "44auFUrGECh2dOIWHyGZyl"
                }
            ]
        },
        "03": {
            "s0": "",
            "s1": [
                {
                    "artist": "Jane Remover",
                    "title": "goldfish",
                    "uri": "7A8YnjMhMrTfVqMRRfayv7"
                },
                {
                    "artist": "Jane Remover",
                    "title": "pretender",
                    "uri": "44auFUrGECh2dOIWHyGZyl"
                },
                {
                    "artist": "Jane Remover",
                    "title": "search party",
                    "uri": "490NAHwXWtwve0t4J2Q0D0"
                }
            ]
        },
        "04": {
            "s0": "",
            "s1": [
                {
                    "artist": "Jane Remover",
                    "title": "kodak moment",
                    "uri": "1OM5kosmreVYutffduC3kW"
                },
                {
                    "artist": "Jane Remover",
                    "title": "buzzcut, daisy",
                    "uri": "1IHWMSs40XqfjcEc5JN9UQ"
                },
                {
                    "artist": "Jane Remover",
                    "title": "champ",
                    "uri": "0yMHRbPsUO7niNMiQidYSj"
                }
            ]
        },
        "05": {
            "s0": "",
            "s1": [
                {
                    "artist": "Jane Remover",
                    "title": "movies for guys",
                    "uri": "1urgZoAjz91vFqPEokA1OR"
                },
                {
                    "artist": "Jane Remover",
                    "title": "goldfish",
                    "uri": "7A8YnjMhMrTfVqMRRfayv7"
                },
                {
                    "artist": "Jane Remover",
                    "title": "homeswitcher",
                    "uri": "3wGDs4CbpDqpsTYyN5pe8o"
                }
            ]
        },
        "06": {
            "s0": "",
            "s1": [
                {
                    "artist": "Jane Remover",
                    "title": "goldfish",
                    "uri": "7A8YnjMhMrTfVqMRRfayv7"
                },
                {
                    "artist": "Jane Remover",
                    "title": "Cage Girl",
                    "uri": "1INxSAGo3BIvfxGBIp7XeM"
                },
                {
                    "artist": "Jane Remover",
                    "title": "search party",
                    "uri": "490NAHwXWtwve0t4J2Q0D0"
                }
            ]
        }
    },
    "jane-remover-26th-may-2023": {
        "00": {
            "s0": "",
            "s1": [
                {
                    "artist": "Jtrapz",
                    "title": "Whats Good",
                    "uri": "4Kjybl0Jx6U6pvKM9YezOd"
                },
                {
                    "artist": "SEVENTEEN",
                    "title": "What's Good",
                    "uri": "76rsUJjmMCbNL3nbbEypUF"
                },
                {
                    "artist": "Solum Prince",
                    "title": "What's Good?",
                    "uri": "5jaBvHulvSMkrNjdRL2jTF"
                }
            ]
        },
        "01": {
            "s0": "",
            "s1": [
                {
                    "artist": "LukeyBaby",
                    "title": "White Noise",
                    "uri": "2tjK8z9KhfnGQ3HQRrPIHJ"
                },
                {
                    "artist": "NSC359",
                    "title": "HVV ohne Ticket",
                    "uri": "38CiMv5bSy9cJhrBZdy9Yi"
                },
                {
                    "artist": "EKEV",
                    "title": "HVNN",
                    "uri": "0MCCWV3XX8nhH3cuDsPhmW"
                }
            ]
        },
        "02": {
            "s0": "",
            "s1": [
                {
                    "artist": "Marta Labrok",
                    "title": "Lane",
                    "uri": "4T5SRdOVkoJ4Lmj7MWnKWG"
                },
                {
                    "artist": "Lane 8",
                    "title": "Woman",
                    "uri": "477nsrJgEucX7WEdxc149q"
                },
                {
                    "artist": "Lane 8",
                    "title": "Just",
                    "uri": "3yYk5jhpqHF6lpIyvjhTRZ"
                }
            ]
        },
        "03": {
            "s0": "",
            "s1": [
                {
                    "artist": "Hamza",
                    "title": "Late Nights",
                    "uri": "79PXEZ5ks0CAytlKtxi4ii"
                },
                {
                    "artist": "K1",
                    "title": "Late Nights",
                    "uri": "4G819fk1XvAlVUtftnVPON"
                },
                {
                    "artist": "ItsArius",
                    "title": "Late Nights",
                    "uri": "6Hhoz2lLQh9IqiYQOEeTyQ"
                }
            ]
        },
        "04": {
            "s0": "",
            "s1": [
                {
                    "artist": "WEEDMANE",
                    "title": "SUICIDE YEAR",
                    "uri": "6hRvewF5MRAsqqxnNs3z2b"
                },
                {
                    "artist": "WEEDMANE",
                    "title": "SUICIDE YEAR - airshade Remix",
                    "uri": "6RwgElqL69RIVhQrKgT4dE"
                },
                {
                    "artist": "framed",
                    "title": "Suicide Yr",
                    "uri": "34VA44arDHajOIl0g27IfK"
                }
            ]
        },
        "05": {
            "s0": [
                {
                    "artist": "Cardi B",
                    "title": "Bodak Yellow",
                    "uri": "6KBYefIoo7KydImq1uUQlL"
                },
                {
                    "artist": "Cardi B",
                    "title": "Bodak Yellow",
                    "uri": "2771LMNxwf62FTAdpJMQfM"
                },
                {
                    "artist": "Cardi B",
                    "title": "Bodak Yellow (feat. Kodak Black)",
                    "uri": "7EUdsWV0Cs8nyTo4R5Ef9b"
                }
            ],
            "s1": [
                {
                    "artist": "Cardi B",
                    "title": "Bodak Yellow",
                    "uri": "6KBYefIoo7KydImq1uUQlL"
                },
                {
                    "artist": "Cardi B",
                    "title": "Bodak Yellow",
                    "uri": "2771LMNxwf62FTAdpJMQfM"
                },
                {
                    "artist": "Cardi B",
                    "title": "Bodak Yellow (feat. Kodak Black)",
                    "uri": "7EUdsWV0Cs8nyTo4R5Ef9b"
                }
            ]
        },
        "06": {
            "s0": "",
            "s1": [
                {
                    "artist": "Ginseng",
                    "title": "she's haunting me",
                    "uri": "27oJpfxSVKfsDPYlNpATpf"
                },
                {
                    "artist": "Ginseng",
                    "title": "she",
                    "uri": "60HnSam30P0oyVqGoKI0Um"
                },
                {
                    "artist": "vowl.",
                    "title": "ink",
                    "uri": "5dc9AkpcWVrd0nXt5FHN6j"
                }
            ]
        },
        "07": {
            "s0": "",
            "s1": [
                {
                    "artist": "Seraphim",
                    "title": "PURGATORY",
                    "uri": "2NAPXTRUMaXW4Pf3606hHL"
                },
                {
                    "artist": "DPR IAN",
                    "title": "Seraph",
                    "uri": "63fKobYkOInUrQL1Kb1oME"
                },
                {
                    "artist": "Sinizter",
                    "title": "ROGUE!",
                    "uri": "5VzcuUMmk1ElMCKQORCkC4"
                }
            ]
        },
        "08": {
            "s0": "",
            "s1": [
                {
                    "artist": "LOVKN",
                    "title": "Holy Rain",
                    "uri": "6CFj3yJ1i8U91Cn7jN0fSI"
                },
                {
                    "artist": "MYSTXRIVL",
                    "title": "Holy Rain",
                    "uri": "6uAXYMxE8d87tRLn7hzexD"
                },
                {
                    "artist": "Holyrayne",
                    "title": "The Shadows are Watching",
                    "uri": "59fMHjDCvpXgj0wUrPWV0C"
                }
            ]
        },
        "09": {
            "s0": [
                {
                    "artist": "Roy Woods",
                    "title": "Get You Good",
                    "uri": "0Hy7GwC7e4FZBWsWnOcuqP"
                },
                {
                    "artist": "Roy Woods",
                    "title": "Get You Good",
                    "uri": "6NVbORJVWfGvIrsi5kwoZx"
                }
            ],
            "s1": [
                {
                    "artist": "Roy Woods",
                    "title": "Get You Good",
                    "uri": "0Hy7GwC7e4FZBWsWnOcuqP"
                },
                {
                    "artist": "Roy Woods",
                    "title": "Get You Good",
                    "uri": "6NVbORJVWfGvIrsi5kwoZx"
                },
                {
                    "artist": "Roy Woods",
                    "title": "Don’t Mind Me",
                    "uri": "1ZsNLqqBzUbDG9LDosVk2p"
                }
            ]
        },
        "10": {
            "s0": [
                {
                    "artist": "Brothel",
                    "title": "Ignore",
                    "uri": "1vpVH5mSVc6q9RicScd97M"
                }
            ],
            "s1": [
                {
                    "artist": "Brothel",
                    "title": "Ignore",
                    "uri": "1vpVH5mSVc6q9RicScd97M"
                },
                {
                    "artist": "Brothel",
                    "title": "Bryanex",
                    "uri": "0JZvnZkiNFHQkLpEDu36AQ"
                },
                {
                    "artist": "Brothel",
                    "title": "Slide",
                    "uri": "1h6tC7XbCucYdyQfN0XYUV"
                }
            ]
        },
        "11": {
            "s0": [
                {
                    "artist": "yenss",
                    "title": "Cold",
                    "uri": "2qHW6ca2Z12Ea7aKO0QXui"
                },
                {
                    "artist": "Ben Yen",
                    "title": "nice n cold",
                    "uri": "2saRg82j6d5EVP6s8eDqSt"
                },
                {
                    "artist": "YENISEI",
                    "title": "Bitter Cold",
                    "uri": "1j6oOdy40Qmllz8tdPh6yb"
                }
            ],
            "s1": [
                {
                    "artist": "yatashigang",
                    "title": "Cold",
                    "uri": "2Cq6LAXdsL5jySnCWinBUc"
                },
                {
                    "artist": "Ryan Perdz",
                    "title": "Cold",
                    "uri": "1Z0jOEVXfSMO2gkqqsLVIY"
                },
                {
                    "artist": "DJ Khalil",
                    "title": "Elevate (feat. Denzel Curry, YBN Cordae, SwaVay, Trevor Rich)",
                    "uri": "6kiauSlWtddVQx4JwJx51p"
                }
            ]
        },
        "12": {
            "s0": "",
            "s1": [
                {
                    "artist": "Clams Casino",
                    "title": "Blast",
                    "uri": "6xr3MVHxQaOtBybv0uD8ir"
                },
                {
                    "artist": "Clams Casino",
                    "title": "I'm God",
                    "uri": "0FVuyC9RP5MACjp4lgU3qZ"
                },
                {
                    "artist": "Clams Casino",
                    "title": "I'm God",
                    "uri": "6SFkLxjZLpK6PNwO91sMES"
                }
            ]
        },
        "13": {
            "s0": "",
            "s1": [
                {
                    "artist": "DJ Diamond",
                    "title": "Dozin",
                    "uri": "2WZews7G2baFSURGmOGMDG"
                },
                {
                    "artist": "Aixion",
                    "title": "Dozin'",
                    "uri": "6lBywzmsxD3F3wDRGxXVc4"
                },
                {
                    "artist": "Kenjiboiii",
                    "title": "Dozin",
                    "uri": "4eMZxXShfCuWceQp8fV9bD"
                }
            ]
        },
        "14": {
            "s0": "",
            "s1": [
                {
                    "artist": "Sven Grosser",
                    "title": "H S V",
                    "uri": "5UvbOXjsJMXVvyTszq0U8v"
                },
                {
                    "artist": "Shanty-Chor Neu Wulmstorf \"De Windjammers\"",
                    "title": "HSV Vereinshymne",
                    "uri": "3qSMwPfUxT7Vb4CFzOxqrd"
                },
                {
                    "artist": "Abschlach",
                    "title": "HSV Vereinshymne",
                    "uri": "37pmHEgrZnFlExZEe548BB"
                }
            ]
        },
        "15": {
            "s0": "",
            "s1": [
                {
                    "artist": "KOHH",
                    "title": "HIROI SEKAI",
                    "uri": "4brCWQboyGVYZxZCE9AJWM"
                },
                {
                    "artist": "Evenings",
                    "title": "Babe",
                    "uri": "7nfGqsJl4A3lXApUI0YIFA"
                },
                {
                    "artist": "Iloveakim",
                    "title": "Babe",
                    "uri": "3s8jQ074bmxZelb2WGMGgs"
                }
            ]
        },
        "16": {
            "s0": "",
            "s1": [
                {
                    "artist": "Bow Wow",
                    "title": "Bow Wow (That's My Name) (feat. Snoop Dogg)",
                    "uri": "3RnLEACttdwU6futFsaflI"
                },
                {
                    "artist": "Bow Wow",
                    "title": "Like You (feat. Ciara)",
                    "uri": "3jEqrIfwKO0M8ALu3TGilF"
                },
                {
                    "artist": "Bow Wow",
                    "title": "Bow Wow (That's My Name) - Radio Edit",
                    "uri": "0tqZy9V0D8RzJKh0XisVMI"
                }
            ]
        },
        "17": {
            "s0": [
                {
                    "artist": "Miley Cyrus",
                    "title": "Tangerine (feat. Big Sean)",
                    "uri": "6NhnZpaiFgnaPXOvYaNEFJ"
                }
            ],
            "s1": [
                {
                    "artist": "Miley Cyrus",
                    "title": "Tangerine (feat. Big Sean)",
                    "uri": "6NhnZpaiFgnaPXOvYaNEFJ"
                },
                {
                    "artist": "Malik",
                    "title": "Tangerines",
                    "uri": "5OqAt7yFGoyAV9PEOAmfa1"
                },
                {
                    "artist": "Declan J Donovan",
                    "title": "Tangerine Skies",
                    "uri": "0HlKVWqNINphxorvga3cRR"
                }
            ]
        },
        "18": {
            "s0": "",
            "s1": [
                {
                    "artist": "Raido",
                    "title": "Aether (Fzpz remix)",
                    "uri": "2r5Jk254j4Wzg31xdgQTIh"
                },
                {
                    "artist": "Aether",
                    "title": "Opti-Mystic - Original Mix",
                    "uri": "13v2daWGPBubosr5aI5Apy"
                },
                {
                    "artist": "Morning Piano",
                    "title": "Aether Mystical",
                    "uri": "3eZMz6zIaD9V4OcJVRZ3kE"
                }
            ]
        }
    },
    "jane-remover-31st-march-2023": {
        "00": {
            "s0": [
                {
                    "artist": "Caroline Polachek",
                    "title": "Welcome To My Island",
                    "uri": "4bp2wYweUPvsBrQfntdYcr"
                },
                {
                    "artist": "Caroline Polachek",
                    "title": "Welcome To My Island - George Daniel & Charli XCX Remix",
                    "uri": "4w2PIlbpP4jhc1S9MHUHzb"
                },
                {
                    "artist": "Caroline Polachek",
                    "title": "Welcome To My Island - George Daniel & Charli XCX Remix",
                    "uri": "2nQeWDP8OA9vFqiCfghot2"
                }
            ],
            "s1": [
                {
                    "artist": "Caroline Polachek",
                    "title": "Welcome To My Island",
                    "uri": "4bp2wYweUPvsBrQfntdYcr"
                },
                {
                    "artist": "Caroline Polachek",
                    "title": "Welcome To My Island",
                    "uri": "2QeUnYtvlfQdfWxzF3b1ud"
                },
                {
                    "artist": "Caroline Polachek",
                    "title": "Welcome To My Island - George Daniel & Charli XCX Remix",
                    "uri": "4w2PIlbpP4jhc1S9MHUHzb"
                }
            ]
        },
        "01": {
            "s0": "",
            "s1": [
                {
                    "artist": "Pitbull",
                    "title": "Free Free Free",
                    "uri": "1hvZ3uUcaCZrcZQXWUBRse"
                },
                {
                    "artist": "Schwarz & Funk",
                    "title": "Free Floating - Beach House Mix",
                    "uri": "5T6AL19l7Pte7kyJ9znzXa"
                },
                {
                    "artist": "Simply Chill",
                    "title": "Free For Life - Chill House Mix",
                    "uri": "0H4jZpT3LdZ3b2pNKLjagJ"
                }
            ]
        },
        "02": {
            "s0": [
                {
                    "artist": "Ellie Goulding",
                    "title": "Fighter Plane",
                    "uri": "0tR881lVeeNQu3zegkYhGq"
                },
                {
                    "artist": "Ellie Goulding",
                    "title": "Fighter Plane",
                    "uri": "38ovzkpHUn1lelhY3zuvLz"
                }
            ],
            "s1": [
                {
                    "artist": "Calvin Harris",
                    "title": "Miracle (with Ellie Goulding)",
                    "uri": "5eTaQYBE1yrActixMAeLcZ"
                },
                {
                    "artist": "Calvin Harris",
                    "title": "Outside (feat. Ellie Goulding)",
                    "uri": "7MmG8p0F9N3C4AXdK6o6Eb"
                },
                {
                    "artist": "Ellie Goulding",
                    "title": "Burn",
                    "uri": "5lF0pHbsJ0QqyIrLweHJPW"
                }
            ]
        },
        "03": {
            "s0": "",
            "s1": [
                {
                    "artist": "Uppermost",
                    "title": "Flashback",
                    "uri": "52P5KaZHtX1tAjErCN8ReC"
                },
                {
                    "artist": "Uppermost",
                    "title": "Beautiful Light",
                    "uri": "72svLiYZ4D14ryt056I66v"
                },
                {
                    "artist": "Uppermost",
                    "title": "Uprising",
                    "uri": "6csM8o9XpHMQJSxUkT7VOs"
                }
            ]
        },
        "04": {
            "s0": [
                {
                    "artist": "Jane Remover",
                    "title": "Royal Blue Walls",
                    "uri": "4AwEBnyhdSFQqPGRRJ3Ph1"
                }
            ],
            "s1": [
                {
                    "artist": "Jane Remover",
                    "title": "Royal Blue Walls",
                    "uri": "4AwEBnyhdSFQqPGRRJ3Ph1"
                },
                {
                    "artist": "Jane Remover",
                    "title": "Cage Girl",
                    "uri": "1INxSAGo3BIvfxGBIp7XeM"
                },
                {
                    "artist": "Jane Remover",
                    "title": "homeswitcher",
                    "uri": "3wGDs4CbpDqpsTYyN5pe8o"
                }
            ]
        },
        "05": {
            "s0": "",
            "s1": [
                {
                    "artist": "Hikaru Utada",
                    "title": "Face My Fears (English Version)",
                    "uri": "0CALOqrkXAE7WB2nyIATLk"
                },
                {
                    "artist": "Hikaru Utada",
                    "title": "First Love",
                    "uri": "39HrUxcvKF3jtLz7fUDWXc"
                },
                {
                    "artist": "Hikaru Utada",
                    "title": "Simple And Clean",
                    "uri": "2G8tfTExxzpRKssKzKwDYV"
                }
            ]
        },
        "06": {
            "s0": [
                {
                    "artist": "Alice Deejay",
                    "title": "Better Off Alone",
                    "uri": "5XVjNRubJUW0iPhhSWpLCj"
                },
                {
                    "artist": "Alice Deejay",
                    "title": "Better Off Alone",
                    "uri": "4u4JMXuhg94qU88lzeiiuq"
                },
                {
                    "artist": "Alice Deejay",
                    "title": "Better Off Alone - Vocal Club RMX",
                    "uri": "5Qzb43ElQH5nrZZPBXEjZF"
                }
            ],
            "s1": [
                {
                    "artist": "Alice Deejay",
                    "title": "Better Off Alone",
                    "uri": "5XVjNRubJUW0iPhhSWpLCj"
                },
                {
                    "artist": "Alice Deejay",
                    "title": "Better Off Alone - Vocal Club RMX",
                    "uri": "5Qzb43ElQH5nrZZPBXEjZF"
                },
                {
                    "artist": "Dance Fruits Music",
                    "title": "Better Off Alone",
                    "uri": "4yKN43pgKLGsoGZWpHpW5A"
                }
            ]
        },
        "07": {
            "s0": "",
            "s1": [
                {
                    "artist": "Arca",
                    "title": "Rakata",
                    "uri": "1yVbARBysb11nskwIzXLIg"
                },
                {
                    "artist": "Arca",
                    "title": "KLK",
                    "uri": "2ZFu40Ik8VsUE9H87W0MmZ"
                },
                {
                    "artist": "Arca",
                    "title": "Rakata",
                    "uri": "0hp5IJ83YpnglsrvGfIhIN"
                }
            ]
        },
        "08": {
            "s0": "",
            "s1": [
                {
                    "artist": "Deftones",
                    "title": "Change (In the House of Flies)",
                    "uri": "51c94ac31swyDQj9B3Lzs3"
                },
                {
                    "artist": "Deftones",
                    "title": "Be Quiet and Drive (Far Away)",
                    "uri": "4Uiw0Sl9yskBaC6P4DcdVD"
                },
                {
                    "artist": "Deftones",
                    "title": "Sextape",
                    "uri": "1EryAkZ0VHstC6haIxVBiE"
                }
            ]
        },
        "09": {
            "s0": "",
            "s1": [
                {
                    "artist": "Burial",
                    "title": "Nova",
                    "uri": "7dYjEwbLJ1B5reoz3lWra0"
                },
                {
                    "artist": "Burial",
                    "title": "Archangel",
                    "uri": "6evpAJCR5GeeHDGgv3aXb3"
                },
                {
                    "artist": "Yogi",
                    "title": "Burial (feat. Pusha T, Moody Good, TrollPhace)",
                    "uri": "7DHX1Ng0V186U2idfFfjGi"
                }
            ]
        }
    },
    "jane-remover-3rd-march-2023": {
        "00": {
            "s0": "",
            "s1": [
                {
                    "artist": "Saint Motel",
                    "title": "Sweet Talk",
                    "uri": "6kcHg7XL6SKyPNd78daRBL"
                },
                {
                    "artist": "Poe the Passenger",
                    "title": "SWEET TALK",
                    "uri": "0BVwUg0kBNy6V4xtdDMA5e"
                },
                {
                    "artist": "Years & Years",
                    "title": "Sweet Talker",
                    "uri": "6FRxFke9VsjXmibGgSeKki"
                }
            ]
        },
        "01": {
            "s0": "",
            "s1": [
                {
                    "artist": "Andrei Munteanu",
                    "title": "Obsessed Remix",
                    "uri": "2dKqefmjMZUyCyrlnEyIuv"
                },
                {
                    "artist": "PØP CULTUR",
                    "title": "Obsessed",
                    "uri": "6uVnKjVno32pFOW8CSonhB"
                },
                {
                    "artist": "Tag Shai",
                    "title": "Obsessed",
                    "uri": "3ke4xgFllNax3xdGKWKMYY"
                }
            ]
        },
        "02": {
            "s0": "",
            "s1": [
                {
                    "artist": "Ariana Grande",
                    "title": "One Last Time",
                    "uri": "7xoUc6faLbCqZO6fQEYprd"
                },
                {
                    "artist": "BAKI",
                    "title": "One Last Time - Hardstyle - Sped Up",
                    "uri": "77vPiErr9IG1oBk58VrHy5"
                },
                {
                    "artist": "Masove",
                    "title": "One Last Time",
                    "uri": "0dl4C3tXqVqdCsVj4pi7AB"
                }
            ]
        },
        "03": {
            "s0": "",
            "s1": [
                {
                    "artist": "Carly Rae Jepsen",
                    "title": "Call Me Maybe",
                    "uri": "20I6sIOMTCkB6w7ryavxtO"
                },
                {
                    "artist": "Hiko",
                    "title": "Call Me Maybe (Sped Up) - Hey I Just Met You",
                    "uri": "4JBq3qXENHuALUXBGt1ey7"
                },
                {
                    "artist": "Scottie",
                    "title": "Call Me Maybe - Acoustic",
                    "uri": "1CSi4vh5zKb3bN2FtXHa8O"
                }
            ]
        },
        "04": {
            "s0": "",
            "s1": [
                {
                    "artist": "Jamiroquai",
                    "title": "Space Cowboy",
                    "uri": "6K53GM9W6Vle5KBwGFVnZM"
                },
                {
                    "artist": "ZillaKami",
                    "title": "Space Cowboy",
                    "uri": "1Ndx4AI3Bco1Ewc84OrOQP"
                },
                {
                    "artist": "Banaroo",
                    "title": "Space Cowboy - Radio Edit",
                    "uri": "0zV9NncXeb3YC1DRRnmRMX"
                }
            ]
        },
        "05": {
            "s0": "",
            "s1": [
                {
                    "artist": "EDITKINGS",
                    "title": "Super Freaky Girl (TikTok Edit) - Remix",
                    "uri": "6X4eCXt7OqqpDpoPZFw3SD"
                },
                {
                    "artist": "KPH",
                    "title": "Super Freaky Girl - Instrumental",
                    "uri": "5CyDZcC55xO6MOx2D7fEqG"
                },
                {
                    "artist": "Evelyn Katrine",
                    "title": "Super Freaky Girl",
                    "uri": "2rV6hxrORZ8Mf30EhizUuo"
                }
            ]
        },
        "06": {
            "s0": [
                {
                    "artist": "Doechii",
                    "title": "Bitch I'm Nice",
                    "uri": "7u5fFWlc7P46XWECmhyqNo"
                },
                {
                    "artist": "Doechii",
                    "title": "Bitch I'm Nice",
                    "uri": "0WuKc8V6cB4LmTRiNcfkun"
                },
                {
                    "artist": "Doechii",
                    "title": "Bitch I'm Nice",
                    "uri": "2bX2TME6UJ8Bq0f80xEned"
                }
            ],
            "s1": [
                {
                    "artist": "Doechii",
                    "title": "Bitch I'm Nice",
                    "uri": "7u5fFWlc7P46XWECmhyqNo"
                },
                {
                    "artist": "Doechii",
                    "title": "Bitch I'm Nice",
                    "uri": "2bX2TME6UJ8Bq0f80xEned"
                },
                {
                    "artist": "Doechii",
                    "title": "Persuasive",
                    "uri": "5MA0iU2dyAFwWUzfyrk2di"
                }
            ]
        },
        "07": {
            "s0": "",
            "s1": [
                {
                    "artist": "Baby Tate",
                    "title": "Pedi",
                    "uri": "4W302qkLfaNUiqkkV6E6HT"
                },
                {
                    "artist": "Baby Tate",
                    "title": "Perfect",
                    "uri": "44AlUStg32yZ3xwhhrUGxq"
                },
                {
                    "artist": "Baby Tate",
                    "title": "Differences",
                    "uri": "7fMwzEtUwvaV45uArYs2Uv"
                }
            ]
        },
        "08": {
            "s0": "",
            "s1": [
                {
                    "artist": "kmoe",
                    "title": "homesick",
                    "uri": "2v3yISHLk0QNStai26hvkw"
                },
                {
                    "artist": "kmoe",
                    "title": "flutter",
                    "uri": "7Bdr6tUWYkwfP9zDV2QsDi"
                },
                {
                    "artist": "Kvmo",
                    "title": "New Generation",
                    "uri": "5lP4FeDP9sBwemONALPwyb"
                }
            ]
        },
        "09": {
            "s0": "",
            "s1": [
                {
                    "artist": "Dazegxd",
                    "title": "tell me",
                    "uri": "0dbh6lEqxq2Fm3CfNYyAK8"
                },
                {
                    "artist": "Salami Rose Joe Louis",
                    "title": "Tell Meeeee",
                    "uri": "6ahcprEQ414ecRGODsVCU6"
                },
                {
                    "artist": "WATEVA",
                    "title": "Tell Me",
                    "uri": "0AQhaNV10aFkzUsfFJfFAs"
                }
            ]
        },
        "10": {
            "s0": "",
            "s1": [
                {
                    "artist": "juno",
                    "title": "la fleur",
                    "uri": "6pZaP9L3hJ04ZdIEEYMPj0"
                },
                {
                    "artist": "juno",
                    "title": "la fleur",
                    "uri": "4m53TbzWODsSbVTYyeeu2T"
                },
                {
                    "artist": "La Fleur",
                    "title": "Tears",
                    "uri": "11XdtbC7flzHfAuBsoXJlG"
                }
            ]
        },
        "11": {
            "s0": "",
            "s1": [
                {
                    "artist": "City Girls",
                    "title": "Twerk (feat. Cardi B)",
                    "uri": "0RRm4OS5ymfZryXBuj0G2m"
                },
                {
                    "artist": "AFISHAL",
                    "title": "Twerk It",
                    "uri": "7tzf02jlu4uhQGgUBpt6Rg"
                },
                {
                    "artist": "Tony Junior",
                    "title": "Twerk Anthem",
                    "uri": "0cZ6KOvnLf0C0GKLti31No"
                }
            ]
        },
        "12": {
            "s0": "",
            "s1": [
                {
                    "artist": "Dissoactive",
                    "title": "On The Run - Original Mix",
                    "uri": "2XxrR6A3XI26tifnyzYSF3"
                },
                {
                    "artist": "Ummet Ozcan",
                    "title": "On The Run",
                    "uri": "3pOp3XkZfDETcswpUPAT7I"
                },
                {
                    "artist": "maXimum Impact music",
                    "title": "On The Run - 2022 Remastered Version",
                    "uri": "2hplicupu3G2wt5zfX6llb"
                }
            ]
        },
        "13": {
            "s0": "",
            "s1": [
                {
                    "artist": "Drake",
                    "title": "Pop Style",
                    "uri": "5mPSyjLatqB00IkPqRlbTE"
                },
                {
                    "artist": "Jack Daily",
                    "title": "Pop Style - Jack Daily Remix",
                    "uri": "3Eugjy9ObAlpPdS2gtOCe1"
                },
                {
                    "artist": "Drake",
                    "title": "Pop Style",
                    "uri": "23NWj2izXAJ4yL6Nah73wf"
                }
            ]
        },
        "14": {
            "s0": "",
            "s1": [
                {
                    "artist": "Jane Remover",
                    "title": "Cage Girl",
                    "uri": "1INxSAGo3BIvfxGBIp7XeM"
                },
                {
                    "artist": "Jane Remover",
                    "title": "movies for guys",
                    "uri": "1urgZoAjz91vFqPEokA1OR"
                },
                {
                    "artist": "Jane Remover",
                    "title": "homeswitcher",
                    "uri": "3wGDs4CbpDqpsTYyN5pe8o"
                }
            ]
        }
    }
}