{
    "bunny-wailer-u-roy-tribute-18th-march-2021": {
        "00": {
            "s0": [
                {
                    "artist": "Hugh Roy",
                    "title": "Wake The Town",
                    "uri": "337OwFvjyEf69b7VPwNxum"
                }
            ],
            "s1": [
                {
                    "artist": "Hugh Roy",
                    "title": "Wake The Town",
                    "uri": "337OwFvjyEf69b7VPwNxum"
                }
            ]
        },
        "01": {
            "s0": [
                {
                    "artist": "Bunny Wailer",
                    "title": "Armagideon (Armagedon)",
                    "uri": "5d98ZIfSvbSMKJnxi9ZYxo"
                }
            ],
            "s1": [
                {
                    "artist": "Bunny Wailer",
                    "title": "Armagideon (Armagedon)",
                    "uri": "5d98ZIfSvbSMKJnxi9ZYxo"
                },
                {
                    "artist": "Bunny Wailer",
                    "title": "Dream Land",
                    "uri": "7vp89zcbYncoBCbX5HA3tZ"
                },
                {
                    "artist": "Bunny Wailer",
                    "title": "Fighting Against Conviction",
                    "uri": "5MKYnizdhDDik45mEncVXu"
                }
            ]
        },
        "02": {
            "s0": [
                {
                    "artist": "U-Roy",
                    "title": "King Tubby's Skank",
                    "uri": "3EEPgO8GbMuu8pDAWotd4Z"
                },
                {
                    "artist": "U-Roy",
                    "title": "King Tubbys Skank",
                    "uri": "5HawjBB8KwKlNeDq5qHWGT"
                },
                {
                    "artist": "U-Roy",
                    "title": "King Tubby Skank",
                    "uri": "0nUrWP73kLO0mGsgWzDoe1"
                }
            ],
            "s1": [
                {
                    "artist": "U-Roy",
                    "title": "King Tubby's Skank",
                    "uri": "3EEPgO8GbMuu8pDAWotd4Z"
                },
                {
                    "artist": "U-Roy",
                    "title": "King Tubby Skank",
                    "uri": "1xazEvM0oL2jpjR1HxxQch"
                },
                {
                    "artist": "U-Roy",
                    "title": "Gorgan Wise",
                    "uri": "5g748jrepoTlQpTFJlXcTk"
                }
            ]
        },
        "03": {
            "s0": "",
            "s1": [
                {
                    "artist": "Hugh Roy",
                    "title": "Catty",
                    "uri": "4v6MHgNQTQY0YsA3PKx5gx"
                }
            ]
        },
        "04": {
            "s0": [
                {
                    "artist": "U-Roy",
                    "title": "Gorgon Wise",
                    "uri": "688zQEbNm0rjvgEkzjjEjP"
                },
                {
                    "artist": "U-Roy",
                    "title": "Gorgon Wise",
                    "uri": "58PoNBbRpR2cY2otgyASB6"
                },
                {
                    "artist": "U-Roy",
                    "title": "Gorgon Wise",
                    "uri": "4f6224kMMosq8sGZxl83Mj"
                }
            ],
            "s1": [
                {
                    "artist": "U-Roy",
                    "title": "Gorgon Wise",
                    "uri": "688zQEbNm0rjvgEkzjjEjP"
                },
                {
                    "artist": "U-Roy",
                    "title": "Gorgon Wise",
                    "uri": "58PoNBbRpR2cY2otgyASB6"
                },
                {
                    "artist": "U-Roy",
                    "title": "Gorgan Wise",
                    "uri": "5g748jrepoTlQpTFJlXcTk"
                }
            ]
        },
        "05": {
            "s0": [
                {
                    "artist": "U-Roy",
                    "title": "Natty Rebel - Remaster 1990",
                    "uri": "5FgdPuK51WBYhuMhV0XIBg"
                },
                {
                    "artist": "U-Roy",
                    "title": "Natty Rebel - Remaster 1990",
                    "uri": "6SCJgGNhzzMb3Sp244UK1w"
                },
                {
                    "artist": "U-Roy",
                    "title": "Natty Rebel",
                    "uri": "0OXqjgWApWQvuZcWTjmhxS"
                }
            ],
            "s1": [
                {
                    "artist": "U-Roy",
                    "title": "Natty Rebel - Remaster 1990",
                    "uri": "5FgdPuK51WBYhuMhV0XIBg"
                },
                {
                    "artist": "U-Roy",
                    "title": "Natty Rebel",
                    "uri": "0OXqjgWApWQvuZcWTjmhxS"
                },
                {
                    "artist": "U-Roy",
                    "title": "Babylon Burning - Remaster 1991",
                    "uri": "5SPpMIiUrZcgJNR5fBoVYk"
                }
            ]
        },
        "06": {
            "s0": [
                {
                    "artist": "U-Roy",
                    "title": "Chalice In The Palace - 1990 Digital Remaster",
                    "uri": "0DS746s6nq0m9S1QL3wHF5"
                },
                {
                    "artist": "U-Roy",
                    "title": "Chalice In The Palace - 1990 Digital Remaster",
                    "uri": "0XHbsFYB6kdzujxZs5bVBj"
                },
                {
                    "artist": "U-Roy",
                    "title": "Chalice In The Palace - Remaster 1991",
                    "uri": "126LF6cekbGCKmz7HIUIoB"
                }
            ],
            "s1": [
                {
                    "artist": "U-Roy",
                    "title": "Chalice In The Palace - 1990 Digital Remaster",
                    "uri": "0XHbsFYB6kdzujxZs5bVBj"
                },
                {
                    "artist": "U-Roy",
                    "title": "Chalice in the Palace",
                    "uri": "5MuNktFTPizRSrhoVuH0WI"
                },
                {
                    "artist": "U-Roy",
                    "title": "Chalice In The Palace - Remaster 1991",
                    "uri": "126LF6cekbGCKmz7HIUIoB"
                }
            ]
        },
        "07": {
            "s0": [
                {
                    "artist": "Bunny Wailer",
                    "title": "Cool Runnings - Live 1995",
                    "uri": "2rjJTYrvtlzRfKzC5KcVo4"
                }
            ],
            "s1": [
                {
                    "artist": "Bunny Wailer",
                    "title": "Cool Runnings - Live 1995",
                    "uri": "2rjJTYrvtlzRfKzC5KcVo4"
                },
                {
                    "artist": "Bunny Wailer",
                    "title": "Cool Running - Live (Remastered)",
                    "uri": "2lR3U71QNAQtrtsyGpokCa"
                },
                {
                    "artist": "Bunny Wailer",
                    "title": "Liberation - Live (Remastered)",
                    "uri": "23s9UMTIerBvrHutaCOtuN"
                }
            ]
        },
        "08": {
            "s0": [
                {
                    "artist": "Bunny Wailer",
                    "title": "Rise And Shine",
                    "uri": "1QXRKnxzaG8YSKud9orA3g"
                },
                {
                    "artist": "Bunny Wailer",
                    "title": "Rise & Shine - Live (Remastered)",
                    "uri": "04jp1CMp1rxGTa4teOJb7z"
                },
                {
                    "artist": "Bunny Wailer",
                    "title": "Rise & Shine - Live 1995",
                    "uri": "76FThhwvO4Uh44jZh9yAKD"
                }
            ],
            "s1": [
                {
                    "artist": "Bunny Wailer",
                    "title": "Rise And Shine",
                    "uri": "1QXRKnxzaG8YSKud9orA3g"
                },
                {
                    "artist": "Bunny Wailer",
                    "title": "Dream Land",
                    "uri": "7vp89zcbYncoBCbX5HA3tZ"
                },
                {
                    "artist": "Bunny Wailer",
                    "title": "Hypocrite",
                    "uri": "0Npt7xXEzMtpkG8d6k7mQ4"
                }
            ]
        },
        "09": {
            "s0": [
                {
                    "artist": "Bunny Wailer",
                    "title": "Blackheart Man",
                    "uri": "7fgP2On62xpLGVNMYORvjn"
                },
                {
                    "artist": "Bunny Wailer",
                    "title": "Rastaman / Blackheart Man - Live (Remastered)",
                    "uri": "2EPTKqr6kSJWkeNQv9Iwuj"
                },
                {
                    "artist": "Bunny Wailer",
                    "title": "Rastaman/Blackheart Man - Live 1995",
                    "uri": "4wWXe3DMGneVcYu6Z9M46e"
                }
            ],
            "s1": [
                {
                    "artist": "Bunny Wailer",
                    "title": "Blackheart Man",
                    "uri": "7fgP2On62xpLGVNMYORvjn"
                },
                {
                    "artist": "Bunny Wailer",
                    "title": "Armagideon (Armagedon)",
                    "uri": "5d98ZIfSvbSMKJnxi9ZYxo"
                },
                {
                    "artist": "Bunny Wailer",
                    "title": "Rastaman / Blackheart Man - Live (Remastered)",
                    "uri": "2EPTKqr6kSJWkeNQv9Iwuj"
                }
            ]
        },
        "10": {
            "s0": [
                {
                    "artist": "Bunny Wailer",
                    "title": "Dream Land",
                    "uri": "1A25zlJuRPGpPajx6eQ5gg"
                },
                {
                    "artist": "Bunny Wailer",
                    "title": "Dream Land",
                    "uri": "04slWSV1GllW54NvgcRvPs"
                },
                {
                    "artist": "Bunny Wailer",
                    "title": "Dream Land",
                    "uri": "7vp89zcbYncoBCbX5HA3tZ"
                }
            ],
            "s1": [
                {
                    "artist": "Bunny Wailer",
                    "title": "Dream Land",
                    "uri": "7vp89zcbYncoBCbX5HA3tZ"
                },
                {
                    "artist": "Bunny Wailer",
                    "title": "Dream Land",
                    "uri": "1A25zlJuRPGpPajx6eQ5gg"
                },
                {
                    "artist": "Bunny Wailer",
                    "title": "Fighting Against Conviction",
                    "uri": "5MKYnizdhDDik45mEncVXu"
                }
            ]
        }
    },
    "johnny-nash-toots-the-maytals-special-18th-november-2020": {
        "00": {
            "s0": [
                {
                    "artist": "Johnny Nash",
                    "title": "I Can See Clearly Now",
                    "uri": "30SCXVFyQGOFMdKnbgJS18"
                },
                {
                    "artist": "Johnny Nash",
                    "title": "I Can See Clearly Now",
                    "uri": "0oCT5rVvMdPPUm0bxG7yzT"
                },
                {
                    "artist": "Johnny Nash",
                    "title": "I Can See Clearly Now - Edit",
                    "uri": "0DcrhZ12WcCqruCs8ibXSf"
                }
            ],
            "s1": [
                {
                    "artist": "Johnny Nash",
                    "title": "I Can See Clearly Now",
                    "uri": "30SCXVFyQGOFMdKnbgJS18"
                },
                {
                    "artist": "Johnny Nash",
                    "title": "I Can See Clearly Now - Edit",
                    "uri": "0DcrhZ12WcCqruCs8ibXSf"
                },
                {
                    "artist": "Uncanny",
                    "title": "Timeless",
                    "uri": "4Lm4QM7QfxCoZr7xlBZhAE"
                }
            ]
        },
        "01": {
            "s0": [
                {
                    "artist": "Johnny Nash",
                    "title": "There Are More Questions Than Answers",
                    "uri": "5cw7lBkPbpFqrfytZhmK3a"
                },
                {
                    "artist": "Johnny Nash",
                    "title": "There Are More Questions Than Answers",
                    "uri": "5nM8blXSt3gaZYdfL4UA32"
                },
                {
                    "artist": "Johnny Nash",
                    "title": "There Are More Questions Than Answers",
                    "uri": "78591xphkfp46CCLiXg3tW"
                }
            ],
            "s1": [
                {
                    "artist": "Johnny Nash",
                    "title": "There Are More Questions Than Answers",
                    "uri": "5cw7lBkPbpFqrfytZhmK3a"
                },
                {
                    "artist": "Johnny Nash",
                    "title": "There Are More Questions Than Answers",
                    "uri": "5nM8blXSt3gaZYdfL4UA32"
                },
                {
                    "artist": "Soundmachine",
                    "title": "There Are More Questions Than Answers (In the Style of Johnny Nash) [Backing Track Version]",
                    "uri": "7LVhaNlWLD6QgAQ82JOCT5"
                }
            ]
        },
        "02": {
            "s0": [
                {
                    "artist": "Toots & The Maytals",
                    "title": "Do The Reggay",
                    "uri": "4IRez9aVdgMovCqghJ2BAN"
                },
                {
                    "artist": "Toots & The Maytals",
                    "title": "Do The Reggay",
                    "uri": "3vlwudRJ1CyfeIxN65kuea"
                },
                {
                    "artist": "Toots & The Maytals",
                    "title": "Do The Reggay",
                    "uri": "0n4txW6YyUk4kmeK8qYkIy"
                }
            ],
            "s1": [
                {
                    "artist": "Toots & The Maytals",
                    "title": "Do The Reggay",
                    "uri": "4IRez9aVdgMovCqghJ2BAN"
                },
                {
                    "artist": "Toots & The Maytals",
                    "title": "Broadway Jungle",
                    "uri": "7nGLAKUK1dlB2tnxIYUtkB"
                },
                {
                    "artist": "Toots & The Maytals",
                    "title": "Spiritual Healing",
                    "uri": "5mwoOwE5twwKyD57WBUKOY"
                }
            ]
        },
        "03": {
            "s0": [
                {
                    "artist": "Toots & The Maytals",
                    "title": "Bam Bam",
                    "uri": "6O8myLzlxlbZSTPwu7XVBu"
                },
                {
                    "artist": "Toots & The Maytals",
                    "title": "Bam Bam",
                    "uri": "7pt9f26kCW2O1zvS9ihVs0"
                },
                {
                    "artist": "Toots & The Maytals",
                    "title": "Bam Bam",
                    "uri": "2jP25OgY1lIWUbuVzINouK"
                }
            ],
            "s1": [
                {
                    "artist": "Toots & The Maytals",
                    "title": "Bam Bam",
                    "uri": "7pt9f26kCW2O1zvS9ihVs0"
                },
                {
                    "artist": "Toots & The Maytals",
                    "title": "Bam Bam",
                    "uri": "2jP25OgY1lIWUbuVzINouK"
                },
                {
                    "artist": "Sister Nancy",
                    "title": "Bam Bam",
                    "uri": "7ixiCZEHWHc8FxaQXQh2P4"
                }
            ]
        },
        "04": {
            "s0": [
                {
                    "artist": "Johnny Nash",
                    "title": "Guava Jelly",
                    "uri": "2YZSJ6AGp83wufUGJBdOUA"
                },
                {
                    "artist": "Johnny Nash",
                    "title": "Guava Jelly",
                    "uri": "3HgiIftu32fA0WMZOtmiyq"
                },
                {
                    "artist": "Johnny Nash",
                    "title": "Guava Jelly",
                    "uri": "3NE1vqk6ny6etx5maTi13r"
                }
            ],
            "s1": [
                {
                    "artist": "Johnny Nash",
                    "title": "Guava Jelly",
                    "uri": "3HgiIftu32fA0WMZOtmiyq"
                },
                {
                    "artist": "Johnny Nash",
                    "title": "Guava Jelly",
                    "uri": "3NE1vqk6ny6etx5maTi13r"
                },
                {
                    "artist": "Johnny Nash",
                    "title": "Guava Jelly",
                    "uri": "0yCVbTzkXhdmJrjyVYwi0i"
                }
            ]
        },
        "05": {
            "s0": [
                {
                    "artist": "Johnny Nash",
                    "title": "Tears on My Pillow",
                    "uri": "34PBygTI3Hjawi2euvRZIV"
                },
                {
                    "artist": "Johnny Nash",
                    "title": "Tears On My Pillow",
                    "uri": "43UvRcDEV8kWHUwR5Y1tou"
                },
                {
                    "artist": "Johnny Nash",
                    "title": "Tears On My Pillow",
                    "uri": "0emH0TBVBV9ODerkgfZVyu"
                }
            ],
            "s1": [
                {
                    "artist": "Johnny Nash",
                    "title": "Tears on My Pillow",
                    "uri": "34PBygTI3Hjawi2euvRZIV"
                },
                {
                    "artist": "Johnny Nash",
                    "title": "Tears On My Pillow",
                    "uri": "0emH0TBVBV9ODerkgfZVyu"
                },
                {
                    "artist": "Johnny Nash",
                    "title": "Tears On My Pillow",
                    "uri": "43UvRcDEV8kWHUwR5Y1tou"
                }
            ]
        },
        "06": {
            "s0": [
                {
                    "artist": "Toots & The Maytals",
                    "title": "54-46 (That's My Number)",
                    "uri": "3mqktr2zCP24NeXzVY0vhe"
                },
                {
                    "artist": "Toots & The Maytals",
                    "title": "54-46 (That's My Number)",
                    "uri": "1tUyILhqf385u0Mut0esPC"
                },
                {
                    "artist": "Toots & The Maytals",
                    "title": "54-46 (That's My Number)",
                    "uri": "0tlcswAprjTe8n4t5wWtw5"
                }
            ],
            "s1": [
                {
                    "artist": "Toots & The Maytals",
                    "title": "54-46 (That's My Number)",
                    "uri": "3mqktr2zCP24NeXzVY0vhe"
                },
                {
                    "artist": "Toots & The Maytals",
                    "title": "54-46 (That's My Number)",
                    "uri": "0tlcswAprjTe8n4t5wWtw5"
                },
                {
                    "artist": "Toots & The Maytals",
                    "title": "54-46 Was My Number",
                    "uri": "1q8gelFgFYUwoWpQV7WNCe"
                }
            ]
        },
        "07": {
            "s0": [
                {
                    "artist": "Toots & The Maytals",
                    "title": "Pressure Drop",
                    "uri": "2EISedV2npKMtvygkykV2r"
                },
                {
                    "artist": "Toots & The Maytals",
                    "title": "Pressure Drop",
                    "uri": "2TRPiN6o3jMRX6u2acRvp0"
                },
                {
                    "artist": "Toots & The Maytals",
                    "title": "Pressure Drop - Single Version",
                    "uri": "2GImcOxFZ0GP49rmPnPOjT"
                }
            ],
            "s1": [
                {
                    "artist": "Toots & The Maytals",
                    "title": "Pressure Drop",
                    "uri": "2EISedV2npKMtvygkykV2r"
                },
                {
                    "artist": "Toots & The Maytals",
                    "title": "Pressure Drop",
                    "uri": "2TRPiN6o3jMRX6u2acRvp0"
                },
                {
                    "artist": "Toots & The Maytals",
                    "title": "Pressure Drop - Single Version",
                    "uri": "2GImcOxFZ0GP49rmPnPOjT"
                }
            ]
        },
        "08": {
            "s0": [
                {
                    "artist": "Johnny Nash",
                    "title": "Stir It Up",
                    "uri": "4UvXfxg1ommzERwd6JVIHv"
                },
                {
                    "artist": "Johnny Nash",
                    "title": "Stir It Up",
                    "uri": "2FMxwBKdRel79WWRwsDMT7"
                },
                {
                    "artist": "Johnny Nash",
                    "title": "STIR IT UP",
                    "uri": "3BT7TYH4vYIOYNrVDxnDuv"
                }
            ],
            "s1": [
                {
                    "artist": "Johnny Nash",
                    "title": "Stir It Up",
                    "uri": "4UvXfxg1ommzERwd6JVIHv"
                },
                {
                    "artist": "Johnny Nash",
                    "title": "STIR IT UP",
                    "uri": "3BT7TYH4vYIOYNrVDxnDuv"
                },
                {
                    "artist": "Soundmachine",
                    "title": "Stir It Up (In the Style of Johnny Nash) [Backing Track Version]",
                    "uri": "2n9H4Dc5qikMb2ltxV3yY0"
                }
            ]
        },
        "09": {
            "s0": [
                {
                    "artist": "Toots & The Maytals",
                    "title": "Sweet And Dandy",
                    "uri": "7pSPnwI0Uk47bUM8g0ubDd"
                },
                {
                    "artist": "Toots & The Maytals",
                    "title": "Sweet And Dandy",
                    "uri": "3UE8enRxYCP3KPD8tPFAD8"
                },
                {
                    "artist": "Toots & The Maytals",
                    "title": "Sweet And Dandy",
                    "uri": "1CZ6EPt26Yx3CXOkuPApyj"
                }
            ],
            "s1": [
                {
                    "artist": "Toots & The Maytals",
                    "title": "Sweet And Dandy",
                    "uri": "3UE8enRxYCP3KPD8tPFAD8"
                },
                {
                    "artist": "Toots & The Maytals",
                    "title": "Sweet And Dandy",
                    "uri": "1CZ6EPt26Yx3CXOkuPApyj"
                },
                {
                    "artist": "Toots & The Maytals",
                    "title": "Pressure Drop",
                    "uri": "2EISedV2npKMtvygkykV2r"
                }
            ]
        },
        "10": {
            "s0": "",
            "s1": [
                {
                    "artist": "Johnny Winter",
                    "title": "Rock Me Baby",
                    "uri": "7jKuO8ZgQibBtlpernJh1Y"
                },
                {
                    "artist": "B.B. King",
                    "title": "Rock Me Baby",
                    "uri": "7wZDztsX5zFWi26ddavyp6"
                },
                {
                    "artist": "B.B. King",
                    "title": "Rock Me Baby",
                    "uri": "1bursm5ZnNHQS55a23h7kR"
                }
            ]
        }
    },
    "nzinga-soundz-26th-may-2021": {
        "00": {
            "s0": [
                {
                    "artist": "Bob Marley & The Wailers",
                    "title": "Running Away",
                    "uri": "2dFx6mVWGJTu4xa1elAQ7n"
                },
                {
                    "artist": "Bob Marley & The Wailers",
                    "title": "Running Away",
                    "uri": "2YFgh1stoJY0C3p7v9dP6b"
                },
                {
                    "artist": "Bob Marley & The Wailers",
                    "title": "Crazy Baldhead / Running Away - Live At The Rainbow Theatre, London / 1977",
                    "uri": "411PukN4UekPx23t979Oe7"
                }
            ],
            "s1": [
                {
                    "artist": "Bob Marley & The Wailers",
                    "title": "Running Away",
                    "uri": "2dFx6mVWGJTu4xa1elAQ7n"
                },
                {
                    "artist": "Bob Marley & The Wailers",
                    "title": "Running Away",
                    "uri": "2YFgh1stoJY0C3p7v9dP6b"
                },
                {
                    "artist": "Bob Marley & The Wailers",
                    "title": "Running Away - Live At The Stanley Theatre, 9/23/1980",
                    "uri": "4zI9A6os8KlTYbKQtpjOz9"
                }
            ]
        },
        "01": {
            "s0": [
                {
                    "artist": "Mighty Diamonds",
                    "title": "Country Living",
                    "uri": "4J7TfPzZVcqc80MSvUTHVw"
                },
                {
                    "artist": "Mighty Diamonds",
                    "title": "Country Living",
                    "uri": "6rmdBJlNWDwB1Kbrf0Z9XO"
                },
                {
                    "artist": "Mighty Diamonds",
                    "title": "Country Living",
                    "uri": "5ndYqLrQY1kBBwQKOUpW3K"
                }
            ],
            "s1": [
                {
                    "artist": "Mighty Diamonds",
                    "title": "Country Living",
                    "uri": "4J7TfPzZVcqc80MSvUTHVw"
                },
                {
                    "artist": "Mighty Diamonds",
                    "title": "Right Time - 2001 Digital Remaster",
                    "uri": "5p3kVMB5spe9fY9CKNAiRm"
                },
                {
                    "artist": "Mighty Diamonds",
                    "title": "I Need A Roof - 2001 Digital Remaster",
                    "uri": "5M9JYhCEojXoMJbWa03i9F"
                }
            ]
        },
        "02": {
            "s0": [
                {
                    "artist": "The Abyssinians",
                    "title": "Declaration of Rights",
                    "uri": "2Iiiy9TUiCGVXl0dUC5YEK"
                },
                {
                    "artist": "The Abyssinians",
                    "title": "Declaration of Rights",
                    "uri": "37WFLcHD7yUpM35mTuMyiE"
                },
                {
                    "artist": "The Abyssinians",
                    "title": "Declaration of Rights - Original Jamaican Mix",
                    "uri": "5NAvt2kJ3rJ8dSBe5haDyz"
                }
            ],
            "s1": [
                {
                    "artist": "The Abyssinians",
                    "title": "Declaration of Rights",
                    "uri": "37WFLcHD7yUpM35mTuMyiE"
                },
                {
                    "artist": "The Abyssinians",
                    "title": "Declaration of Rights",
                    "uri": "2Iiiy9TUiCGVXl0dUC5YEK"
                },
                {
                    "artist": "The Abyssinians",
                    "title": "Declaration of Rights - Original Jamaican Mix",
                    "uri": "5NAvt2kJ3rJ8dSBe5haDyz"
                }
            ]
        },
        "03": {
            "s0": [
                {
                    "artist": "Dennis Brown",
                    "title": "Revolution",
                    "uri": "14uaxEtvwwTR2WnnvAfaj9"
                },
                {
                    "artist": "Dennis Brown",
                    "title": "Revolution",
                    "uri": "1nsEptcDye2MUjMJQ1N5Rh"
                },
                {
                    "artist": "Dennis Brown",
                    "title": "Revolution",
                    "uri": "5dSZuMBRaW4tJvTkC6JZF8"
                }
            ],
            "s1": [
                {
                    "artist": "Dennis Brown",
                    "title": "Revolution",
                    "uri": "14uaxEtvwwTR2WnnvAfaj9"
                },
                {
                    "artist": "Dennis Brown",
                    "title": "Revolution",
                    "uri": "1nsEptcDye2MUjMJQ1N5Rh"
                },
                {
                    "artist": "Dennis Brown",
                    "title": "Revolution",
                    "uri": "6RlYGyL7QxPL8FmmIWKDBa"
                }
            ]
        }
    },
    "nzinga-soundz-28th-july-2021": {
        "00": {
            "s0": "",
            "s1": [
                {
                    "artist": "Fela Ransome-Kuti & His Koola Lobitos",
                    "title": "Nigerian Independence",
                    "uri": "5j3gm4BtN6p38sMycSB5Fr"
                },
                {
                    "artist": "Fela Kuti",
                    "title": "Onifere No. 2",
                    "uri": "0ZjVr4IJfTZnGFve214vs6"
                },
                {
                    "artist": "Fela Kuti",
                    "title": "Water No Get Enemy",
                    "uri": "2oWex6rYoQ7Bl2D9zG8d3F"
                }
            ]
        },
        "01": {
            "s0": [
                {
                    "artist": "Jimmy Cliff",
                    "title": "King Of Kings",
                    "uri": "0uAuE6vl6mi5t69ONcSglj"
                },
                {
                    "artist": "Jimmy Cliff",
                    "title": "King Of Kings (1962 Single Version)",
                    "uri": "3RRzu8l13IHMD8vf81abTX"
                },
                {
                    "artist": "Jimmy Cliff",
                    "title": "King Of Kings (1962 Beverley's Records Single Remastered)",
                    "uri": "66ehZtmJCyjV8lU7u4pyIf"
                }
            ],
            "s1": [
                {
                    "artist": "Jimmy Cliff",
                    "title": "You Can Get It If You Really Want",
                    "uri": "6IwTuQuQ4suJTQ43plwZef"
                },
                {
                    "artist": "Jimmy Cliff",
                    "title": "Rebel In Me",
                    "uri": "31LyiJGtzOgt8I1YoIASV2"
                },
                {
                    "artist": "Jimmy Cliff",
                    "title": "Journey",
                    "uri": "0wVc8w8KViavwhlrWiHIAE"
                }
            ]
        },
        "02": {
            "s0": [
                {
                    "artist": "E.T. Mensah",
                    "title": "Ghana Freedom",
                    "uri": "5TI7ut89bTHEeobd9y55Ni"
                },
                {
                    "artist": "E.T. Mensah",
                    "title": "Ghana Freedom",
                    "uri": "1ACXXD26Ul7dO0TOuqTULV"
                },
                {
                    "artist": "E.T. Mensah Of Ghana",
                    "title": "Ghana Freedom",
                    "uri": "7FwZdzOjUyRj5ZjCuMNSzy"
                }
            ],
            "s1": [
                {
                    "artist": "E.T. Mensah",
                    "title": "Ghana Freedom",
                    "uri": "5TI7ut89bTHEeobd9y55Ni"
                },
                {
                    "artist": "E.T. Mensah",
                    "title": "Ghana-Guinea-Mali",
                    "uri": "4tgd4kF2ndZja6t5LZvBGl"
                },
                {
                    "artist": "E.T. Mensah & The Tempos",
                    "title": "Ghana Freedom",
                    "uri": "791pqO4X8XRAxYHm4hpKg5"
                }
            ]
        },
        "03": {
            "s0": [
                {
                    "artist": "Lord Kitchener",
                    "title": "Birth Of Ghana (6th March, 1957)",
                    "uri": "6360P6fxt5AJx427axUY59"
                }
            ],
            "s1": [
                {
                    "artist": "Lord Kitchener",
                    "title": "Birth of Ghana",
                    "uri": "0HFYcmjhjWUOb5DC0uA36t"
                },
                {
                    "artist": "Lord Kitchener",
                    "title": "Birth of Ghana",
                    "uri": "3wUf3OG4X2ltZp9znbWzW4"
                },
                {
                    "artist": "Lord Kitchener",
                    "title": "Birth of Ghana",
                    "uri": "5by5bJ2wc7YeAGrlSKbEMb"
                }
            ]
        },
        "04": {
            "s0": "",
            "s1": [
                {
                    "artist": "Jimmy Cliff",
                    "title": "I Can See Clearly Now",
                    "uri": "2RcbRwAFUxaiO3rszuEqsz"
                },
                {
                    "artist": "Jimmy Cliff",
                    "title": "You Can Get It If You Really Want",
                    "uri": "6IwTuQuQ4suJTQ43plwZef"
                },
                {
                    "artist": "Jimmy Cliff",
                    "title": "Rebel In Me",
                    "uri": "31LyiJGtzOgt8I1YoIASV2"
                }
            ]
        },
        "05": {
            "s0": [
                {
                    "artist": "African Jazz",
                    "title": "Vive Patrice Lumumba",
                    "uri": "1v9GjwMVAMeOJgXIKhM42H"
                }
            ],
            "s1": [
                {
                    "artist": "African Jazz",
                    "title": "Vive Patrice Lumumba",
                    "uri": "1v9GjwMVAMeOJgXIKhM42H"
                },
                {
                    "artist": "Clan African Jazz",
                    "title": "Indépendance Tchatcha",
                    "uri": "3E0MtVfCdOLqHA038ynRe8"
                },
                {
                    "artist": "TPOK Jazz",
                    "title": "Likambo Ya Ngana",
                    "uri": "5Oz9Qshy4fTbVzZNcefoS8"
                }
            ]
        },
        "06": {
            "s0": "",
            "s1": [
                {
                    "artist": "E. C. Arinze",
                    "title": "Freedom Highlife",
                    "uri": "5BqfBbuKhUcrHEm1Hc24cx"
                },
                {
                    "artist": "E. C. Arinze",
                    "title": "Chukwu Fulum Nanya",
                    "uri": "4ibE98olr55yHO8v4Y20A1"
                },
                {
                    "artist": "E. C. Arinze",
                    "title": "Lumumba Calypso",
                    "uri": "4t4WZuMycrm3D1U9IA24Up"
                }
            ]
        },
        "07": {
            "s0": [
                {
                    "artist": "Mighty Sparrow",
                    "title": "Our Model Nation",
                    "uri": "1rxRU0Ub8ded2bhwkBxDMI"
                }
            ],
            "s1": [
                {
                    "artist": "Mighty Sparrow",
                    "title": "Invade South Africa",
                    "uri": "0nGvxboj4UqvimlhYKmS3v"
                },
                {
                    "artist": "Mighty Sparrow",
                    "title": "Jamaica Farewell - Medley",
                    "uri": "4KbnJCo6aZMv80OjkAtTrK"
                },
                {
                    "artist": "Mighty Sparrow",
                    "title": "Cockeyed Rooster",
                    "uri": "4J2fJaPUyNFKSYe9PXFs73"
                }
            ]
        },
        "08": {
            "s0": [
                {
                    "artist": "Derrick Morgan",
                    "title": "Forward March",
                    "uri": "3dLqhAZUF01vjHXFZFNiF0"
                },
                {
                    "artist": "Derrick Morgan",
                    "title": "Forward March (with The Beverley's All-Stars)",
                    "uri": "47iG4JDwtYo5tyd6jgJQ6N"
                },
                {
                    "artist": "Derrick Morgan",
                    "title": "Forward March (with The Beverley's All-Stars)",
                    "uri": "6uvLlO5HCvHt8HyZgMorKT"
                }
            ],
            "s1": [
                {
                    "artist": "Derrick Morgan",
                    "title": "Forward March",
                    "uri": "3dLqhAZUF01vjHXFZFNiF0"
                },
                {
                    "artist": "Derrick Morgan",
                    "title": "Forward March (with The Beverley's All-Stars)",
                    "uri": "47iG4JDwtYo5tyd6jgJQ6N"
                },
                {
                    "artist": "Derrick Morgan",
                    "title": "Forward March (with The Beverley's All-Stars)",
                    "uri": "6uvLlO5HCvHt8HyZgMorKT"
                }
            ]
        },
        "09": {
            "s0": [
                {
                    "artist": "Lord Creator",
                    "title": "Independent Jamaica Calypso",
                    "uri": "2ZysIi1H6l18TJDSwOjY0m"
                },
                {
                    "artist": "Lord Creator",
                    "title": "Independent Jamaica",
                    "uri": "05vdIdaJoMINvADjpF0gWg"
                },
                {
                    "artist": "Lord Creator",
                    "title": "Independent Jamaica (with The Joe Williams Orchestra)",
                    "uri": "2PszY7htSt2mkA4P29IRNs"
                }
            ],
            "s1": [
                {
                    "artist": "Lord Creator",
                    "title": "Independent Jamaica",
                    "uri": "31lojyLL7OCxDNpavWh2p7"
                },
                {
                    "artist": "Lord Creator",
                    "title": "Independent Jamaica (with The Joe Williams Orchestra)",
                    "uri": "2PszY7htSt2mkA4P29IRNs"
                },
                {
                    "artist": "Lord Creator",
                    "title": "Big Bamboo - Remastered",
                    "uri": "2ZLFZXg2USaVzWTKrj5g35"
                }
            ]
        },
        "10": {
            "s0": "",
            "s1": [
                {
                    "artist": "K.O.G",
                    "title": "Ebenezer - Aroop Roy Remix",
                    "uri": "6EG629nDAf95v2y7tFrmgW"
                },
                {
                    "artist": "Isambulo Senkosi",
                    "title": "Uyindoda",
                    "uri": "5GrDHp1g17Iyoo9aNUcjZ0"
                },
                {
                    "artist": "Pastor Lungi Ndala",
                    "title": "Ebenezer (Reprise)",
                    "uri": "1QBiM0vfHZUwq9JHXIuVQe"
                }
            ]
        },
        "11": {
            "s0": "",
            "s1": [
                {
                    "artist": "Grand Kalle",
                    "title": "Indépendance Cha Cha",
                    "uri": "3kVN8ze4Nfh3nfa8ZUxfpH"
                },
                {
                    "artist": "Grand Kalle",
                    "title": "Indépendance Cha-Cha",
                    "uri": "2LMSNgRC2q0j6yWGOgHWrG"
                },
                {
                    "artist": "Grand Kalle Et l'African Jazz",
                    "title": "Independance Cha-Cha",
                    "uri": "49cfQW8wnSTOeNuPZsmqXf"
                }
            ]
        }
    },
    "nzinga-soundz-29th-april-2021": {
        "00": {
            "s0": [
                {
                    "artist": "Diana Ross",
                    "title": "I'm Coming Out - Original CHIC Mix",
                    "uri": "1HoZjhl0cjWU3MfUMCc8cl"
                },
                {
                    "artist": "Diana Ross",
                    "title": "I'm Coming Out - Original CHIC Mix",
                    "uri": "2Pc77cPgbYMpCKfHRUIKB9"
                },
                {
                    "artist": "Diana Ross",
                    "title": "I'm Coming Out - Maurice's Club Mix",
                    "uri": "11ymMF8I1vBYKIj0qsfMf7"
                }
            ],
            "s1": [
                {
                    "artist": "Diana Ross",
                    "title": "I'm Coming Out",
                    "uri": "3SnGymj6ijE2iuUfWxLo1q"
                },
                {
                    "artist": "Diana Ross",
                    "title": "I'm Coming Out",
                    "uri": "0WBoGdKqK3Hlzt65o5vQqA"
                },
                {
                    "artist": "Diana Ross",
                    "title": "I'm Coming Out / Upside Down - Chris Cox Remix Radio Edit",
                    "uri": "1DjLQFQRBsm9D8aCO4FqR2"
                }
            ]
        },
        "01": {
            "s0": [
                {
                    "artist": "The Notorious B.I.G.",
                    "title": "Mo Money Mo Problems (feat. Puff Daddy & Mase) - Radio Mix; 2014 Remaster",
                    "uri": "4twB8kC49VFnvgCdCrOskb"
                },
                {
                    "artist": "The Notorious B.I.G.",
                    "title": "Mo Money Mo Problems (feat. Puff Daddy & Mase) - Radio Mix; 2014 Remaster",
                    "uri": "6liHdwbKoORg14DlIT8ObF"
                }
            ],
            "s1": [
                {
                    "artist": "The Notorious B.I.G.",
                    "title": "Mo Money Mo Problems (feat. Puff Daddy & Mase) - 2014 Remaster",
                    "uri": "4INDiWSKvqSKDEu7mh8HFz"
                },
                {
                    "artist": "The Notorious B.I.G.",
                    "title": "Mo Money Mo Problems (Stripped Version)",
                    "uri": "4FUA2C0x6UEcw7YGWNs7oM"
                },
                {
                    "artist": "The Notorious B.I.G.",
                    "title": "Mo Money Mo Problems (feat. Puff Daddy, Mase) - 2005 Remaster",
                    "uri": "4h1T8pUzl9VtudWWlVAxxz"
                }
            ]
        },
        "02": {
            "s0": [
                {
                    "artist": "Prince",
                    "title": "I Feel for You",
                    "uri": "0mchygV3fgDtjiu8LPxiDO"
                },
                {
                    "artist": "Prince",
                    "title": "I Feel for You",
                    "uri": "0bNPzbyaT9npwhIP8d2Rsi"
                },
                {
                    "artist": "Prince",
                    "title": "I Feel for You - Acoustic Demo",
                    "uri": "4zMY0BDdpHRHLEHCehLadE"
                }
            ],
            "s1": [
                {
                    "artist": "Prince",
                    "title": "I Feel for You",
                    "uri": "0bNPzbyaT9npwhIP8d2Rsi"
                },
                {
                    "artist": "Prince",
                    "title": "I Feel for You - Acoustic Demo",
                    "uri": "4zMY0BDdpHRHLEHCehLadE"
                },
                {
                    "artist": "PayRoll",
                    "title": "Save The Night",
                    "uri": "4GDe37BafbLU0rOh8MUHOF"
                }
            ]
        },
        "03": {
            "s0": [
                {
                    "artist": "Chaka Khan",
                    "title": "I Feel for You",
                    "uri": "5yR9u8QiOt8hJaddv32oo7"
                },
                {
                    "artist": "Chaka Khan",
                    "title": "I Feel for You",
                    "uri": "7DCiOOtP3baRrHoSzlkNuj"
                },
                {
                    "artist": "Chaka Khan",
                    "title": "This Is My Night",
                    "uri": "1EZmeztCbpOM1vqDlGyJLQ"
                }
            ],
            "s1": [
                {
                    "artist": "Chaka Khan",
                    "title": "I Feel for You",
                    "uri": "5yR9u8QiOt8hJaddv32oo7"
                },
                {
                    "artist": "Chaka Khan",
                    "title": "I Feel for You",
                    "uri": "7DCiOOtP3baRrHoSzlkNuj"
                },
                {
                    "artist": "Homeboy Sandman",
                    "title": "Watchu Want from Me?",
                    "uri": "1fWoZvTl08GEQCCl3aVQDU"
                }
            ]
        },
        "04": {
            "s0": "",
            "s1": [
                {
                    "artist": "Betty Wright",
                    "title": "Shoorah! Shoorah!",
                    "uri": "1X9povBxQkI1ojRA893fv8"
                },
                {
                    "artist": "Betty Wright",
                    "title": "Girls Can't Do What the Guys Do",
                    "uri": "2geMYfXFhqZFMdrF08XSLz"
                },
                {
                    "artist": "Betty Wright",
                    "title": "No Pain, (No Gain)",
                    "uri": "5ze2tIC1kKvaFFf0nP9iNR"
                }
            ]
        },
        "05": {
            "s0": "",
            "s1": [
                {
                    "artist": "John Holt",
                    "title": "Sister Big Stuff",
                    "uri": "16rv237gUx7SmsFxcs0q9l"
                },
                {
                    "artist": "John Holt",
                    "title": "Sister Big Stuff",
                    "uri": "028ARUhVE9NpsVPX8V1WWy"
                },
                {
                    "artist": "John Holt",
                    "title": "Sister Big Stuff",
                    "uri": "4hMTc2gDhPDyeol4xY56Bs"
                }
            ]
        },
        "06": {
            "s0": [
                {
                    "artist": "Sanchez",
                    "title": "I Can't Wait",
                    "uri": "0lmEx9HcHVUbYGMHiWePXN"
                },
                {
                    "artist": "Sanchez",
                    "title": "I Can't Wait",
                    "uri": "6i5PKP70AR5FJX3yuion22"
                },
                {
                    "artist": "Sanchez",
                    "title": "Give It A Chance",
                    "uri": "3s4dS0BlylDQGL27x1SrDp"
                }
            ],
            "s1": [
                {
                    "artist": "Sanchez",
                    "title": "I Can't Wait",
                    "uri": "0lmEx9HcHVUbYGMHiWePXN"
                },
                {
                    "artist": "Sanchez",
                    "title": "I Can't Wait",
                    "uri": "4WPp6RQ6KFKhatZYRU6zSt"
                },
                {
                    "artist": "Sanchez",
                    "title": "I Can't Wait",
                    "uri": "6i5PKP70AR5FJX3yuion22"
                }
            ]
        },
        "07": {
            "s0": [
                {
                    "artist": "Beres Hammond",
                    "title": "Tempted to Touch",
                    "uri": "24kv7kR0Cz8ZBWFx4Kq50A"
                },
                {
                    "artist": "Beres Hammond",
                    "title": "Tempted To Touch",
                    "uri": "5CT9ATPA5GSAuvKKOjnjFx"
                },
                {
                    "artist": "Beres Hammond",
                    "title": "Tempted To Touch",
                    "uri": "72icdIoTT0nJ1614LYti5p"
                }
            ],
            "s1": [
                {
                    "artist": "Beres Hammond",
                    "title": "Tempted to Touch",
                    "uri": "24kv7kR0Cz8ZBWFx4Kq50A"
                },
                {
                    "artist": "Beres Hammond",
                    "title": "Tempted To Touch",
                    "uri": "5CT9ATPA5GSAuvKKOjnjFx"
                },
                {
                    "artist": "Beres Hammond",
                    "title": "Rock Away",
                    "uri": "2RlVyAjLnGJQYp7uzpfUta"
                }
            ]
        },
        "08": {
            "s0": [
                {
                    "artist": "CHIC",
                    "title": "Good Times",
                    "uri": "0G3fbPbE1vGeABDEZF0jeG"
                },
                {
                    "artist": "CHIC",
                    "title": "Good Times - 2018 Remaster",
                    "uri": "4N3stlRuz5cBNI4J4vDJ18"
                },
                {
                    "artist": "CHIC",
                    "title": "Good Times - Original 12\" Mix; 2006 Remaster",
                    "uri": "0XYm6E59GxzX2kc5RrhjcY"
                }
            ],
            "s1": [
                {
                    "artist": "CHIC",
                    "title": "Good Times",
                    "uri": "0G3fbPbE1vGeABDEZF0jeG"
                },
                {
                    "artist": "CHIC",
                    "title": "Good Times - 2018 Remaster",
                    "uri": "4N3stlRuz5cBNI4J4vDJ18"
                },
                {
                    "artist": "Shotgun Willy",
                    "title": "Betty Crocker",
                    "uri": "1Rywx5s6XYWFhxyItRJ7Pb"
                }
            ]
        },
        "09": {
            "s0": [
                {
                    "artist": "The Sugarhill Gang",
                    "title": "Rapper's Delight - Long Version",
                    "uri": "7hqpYgtDckN5wX0jxaaAPx"
                },
                {
                    "artist": "The Sugarhill Gang",
                    "title": "Rapper's Delight - Long Version",
                    "uri": "0RxphrRef802DdWKfTZiVG"
                },
                {
                    "artist": "The Sugarhill Gang",
                    "title": "Rapper's Delight - Long Version",
                    "uri": "3VkW0HdLF1yWQpjIdPf1pT"
                }
            ],
            "s1": [
                {
                    "artist": "The Sugarhill Gang",
                    "title": "Rapper's Delight",
                    "uri": "4IUVLtJEf5k9PIXXTlZy9L"
                },
                {
                    "artist": "The Sugarhill Gang",
                    "title": "Rapper's Delight - Long Version",
                    "uri": "7hqpYgtDckN5wX0jxaaAPx"
                },
                {
                    "artist": "The Sugarhill Gang",
                    "title": "Rapper's Delight - Single Version",
                    "uri": "0tm6gsXe0LSm9zeSspyMQu"
                }
            ]
        },
        "10": {
            "s0": [
                {
                    "artist": "Charles Wright & The Watts 103rd Street Rhythm Band",
                    "title": "Express Yourself",
                    "uri": "4pW3aTX3kAmOaPJfc9UM12"
                },
                {
                    "artist": "Charles Wright",
                    "title": "Express Yourself",
                    "uri": "271NofhzcQo2QHGZ4ZGnV7"
                },
                {
                    "artist": "Charles Wright & The Watts 103rd Street Rhythm Band",
                    "title": "Express Yourself - Remastered Version",
                    "uri": "6gQZKkphKIMxZgca5r7ImA"
                }
            ],
            "s1": [
                {
                    "artist": "Charles Wright",
                    "title": "Express Yourself",
                    "uri": "271NofhzcQo2QHGZ4ZGnV7"
                },
                {
                    "artist": "Charles Wright & The Watts 103rd Street Rhythm Band",
                    "title": "Express Yourself",
                    "uri": "4pW3aTX3kAmOaPJfc9UM12"
                },
                {
                    "artist": "Charles Wright & The Watts 103rd Street Rhythm Band",
                    "title": "Express Yourself - Remastered Version",
                    "uri": "6gQZKkphKIMxZgca5r7ImA"
                }
            ]
        },
        "11": {
            "s0": "",
            "s1": [
                {
                    "artist": "N.W.A.",
                    "title": "Express Yourself",
                    "uri": "52IuMfbQa9aqRPz2oYPAI8"
                },
                {
                    "artist": "N.W.A.",
                    "title": "Express Yourself",
                    "uri": "55JYAswiVAIhO8mK2VVLe1"
                },
                {
                    "artist": "N.W.A.",
                    "title": "Express Yourself - Remix",
                    "uri": "6NLLIPKjqFRnbCorRNTEHe"
                }
            ]
        },
        "12": {
            "s0": [
                {
                    "artist": "Stevie Wonder",
                    "title": "As",
                    "uri": "13toFl1UwJPsRxDiD9jgtn"
                },
                {
                    "artist": "Stevie Wonder",
                    "title": "As - Edit",
                    "uri": "7x1xhZiC2pCeqyg9rqoiLS"
                },
                {
                    "artist": "Stevie Wonder",
                    "title": "As",
                    "uri": "3hFh4tsMFhskEXlJ5DCzsG"
                }
            ],
            "s1": [
                {
                    "artist": "Stevie Wonder",
                    "title": "As",
                    "uri": "13toFl1UwJPsRxDiD9jgtn"
                },
                {
                    "artist": "Stevie Wonder",
                    "title": "As",
                    "uri": "3hFh4tsMFhskEXlJ5DCzsG"
                },
                {
                    "artist": "Kevin Gates",
                    "title": "Get up on My Level",
                    "uri": "6WYLTRkDw5PZj9vzI6Vnjq"
                }
            ]
        },
        "13": {
            "s0": [
                {
                    "artist": "George Michael",
                    "title": "As",
                    "uri": "7r3KzVwHtr2iMZtqJvFn9A"
                },
                {
                    "artist": "George Michael",
                    "title": "As",
                    "uri": "22WJbbti5hZkY7J8jwVX9o"
                },
                {
                    "artist": "George Michael",
                    "title": "Desafinado (with Astrud Gilberto)",
                    "uri": "1dBjIOqSrvbc5ovzKHl8EL"
                }
            ],
            "s1": [
                {
                    "artist": "George Michael",
                    "title": "As",
                    "uri": "7r3KzVwHtr2iMZtqJvFn9A"
                },
                {
                    "artist": "George Michael",
                    "title": "As",
                    "uri": "22WJbbti5hZkY7J8jwVX9o"
                },
                {
                    "artist": "Giacomo Puccini",
                    "title": "Turandot / Act III: Giacomo PUCCINI : Turandot « Nessun dorma »",
                    "uri": "1UXvqMzK9ugo0nWNDmlEfJ"
                }
            ]
        }
    },
    "nzinga-soundz-30th-june-2021": {
        "00": {
            "s0": [
                {
                    "artist": "Betty Wright",
                    "title": "Smother Me With Your Love",
                    "uri": "3Lq4w9xldZrInPVjvMUb4G"
                },
                {
                    "artist": "Betty Wright",
                    "title": "Smother Me with Your Love",
                    "uri": "1qBS5n6BaEQPsQCOcv6nnf"
                }
            ],
            "s1": [
                {
                    "artist": "Betty Wright",
                    "title": "Smother Me With Your Love",
                    "uri": "3Lq4w9xldZrInPVjvMUb4G"
                },
                {
                    "artist": "Betty Wright",
                    "title": "All Your Kissin' Sho' Don't Make True Lovin'",
                    "uri": "5uUN2YyyaD6n9QoksGOG5x"
                },
                {
                    "artist": "Betty Wright",
                    "title": "Medley: Clean up Woman / Pillow Talk / You Got the Love / Mr. Melody / Midnight at the Oasis / Me and Mrs. Jones / You Are My Sunshine / Let's Get Married Today - Live",
                    "uri": "3QfZmcvUqs68LczTglzIZ1"
                }
            ]
        },
        "01": {
            "s0": "",
            "s1": [
                {
                    "artist": "Damian Marley",
                    "title": "Welcome To Jamrock",
                    "uri": "22AbXxQbMdVqEz7xJjhccG"
                },
                {
                    "artist": "Damian Marley",
                    "title": "Welcome To Jamrock",
                    "uri": "7sDbMmWxaErta2JbxKMu3Y"
                },
                {
                    "artist": "Damian Marley",
                    "title": "Me Name Jr. Gong",
                    "uri": "3RAjbhz2rNIAyujNyumABN"
                }
            ]
        },
        "02": {
            "s0": [
                {
                    "artist": "Little John",
                    "title": "Janet Sinclair",
                    "uri": "4SWajP2db0KXX6fAOp0aWY"
                }
            ],
            "s1": [
                {
                    "artist": "Little John",
                    "title": "Janet Sinclair",
                    "uri": "4SWajP2db0KXX6fAOp0aWY"
                },
                {
                    "artist": "Karen song",
                    "title": "Little John",
                    "uri": "1HdjWKtEQk1YZLvSOaH6V5"
                },
                {
                    "artist": "Markus Steinberg",
                    "title": "Little Johann",
                    "uri": "1Itd9kAnXLm0q2wTNEVBCC"
                }
            ]
        },
        "03": {
            "s0": [
                {
                    "artist": "Buju Banton",
                    "title": "Driver A",
                    "uri": "2ANi4KpXrvkbPgxWv0BcI5"
                },
                {
                    "artist": "Buju Banton",
                    "title": "Driver A",
                    "uri": "36FpiM9OWKkw4gMJnqYSzG"
                }
            ],
            "s1": [
                {
                    "artist": "Buju Banton",
                    "title": "Driver A",
                    "uri": "2ANi4KpXrvkbPgxWv0BcI5"
                },
                {
                    "artist": "Buju Banton",
                    "title": "Driver",
                    "uri": "2pgweUSbAKorya9t7M4s5I"
                },
                {
                    "artist": "Driver",
                    "title": "Buju Banton",
                    "uri": "7LyXNJXGutz7dCXjeTQjXw"
                }
            ]
        },
        "04": {
            "s0": [
                {
                    "artist": "Rygin King",
                    "title": "Things Go Change",
                    "uri": "2WZ2svUwcPAz3w0e8Oriu8"
                },
                {
                    "artist": "Rygin King",
                    "title": "Things Go Change",
                    "uri": "7wjFBZKYDP6gRI8wIYikHz"
                },
                {
                    "artist": "Rygin King",
                    "title": "Things Go Change",
                    "uri": "3VPJd2xBOUtyYUokUCyR3Y"
                }
            ],
            "s1": [
                {
                    "artist": "Rygin King",
                    "title": "Things Go Change",
                    "uri": "2WZ2svUwcPAz3w0e8Oriu8"
                },
                {
                    "artist": "Rygin King",
                    "title": "Things Go Change",
                    "uri": "0Q1RZDRFkz5OtqV9OQzVN6"
                },
                {
                    "artist": "Rygin King",
                    "title": "Things Go Change",
                    "uri": "7wjFBZKYDP6gRI8wIYikHz"
                }
            ]
        },
        "05": {
            "s0": [
                {
                    "artist": "Shirley & Lee",
                    "title": "Let The Good Times Roll",
                    "uri": "2ePDfIXoP2HmC1hfsujb2J"
                },
                {
                    "artist": "Shirley & Lee",
                    "title": "Let the Good Times Roll",
                    "uri": "5NsflNel1jV4i52IZ2kKYy"
                },
                {
                    "artist": "Shirley & Lee",
                    "title": "Let the Good Times Roll",
                    "uri": "48UygVtYSfcjeEyCtNR8nI"
                }
            ],
            "s1": [
                {
                    "artist": "Shirley & Lee",
                    "title": "Let The Good Times Roll",
                    "uri": "2ePDfIXoP2HmC1hfsujb2J"
                },
                {
                    "artist": "Shirley & Lee",
                    "title": "Let the Good Times Roll",
                    "uri": "5NsflNel1jV4i52IZ2kKYy"
                },
                {
                    "artist": "Shirley & Lee",
                    "title": "Let the Good Times Roll",
                    "uri": "48UygVtYSfcjeEyCtNR8nI"
                }
            ]
        }
    }
}